{"version": 0.6, "generator": "Overpass API 0.7.62.5 1bd436f1", "osm3s": {"timestamp_osm_base": "2025-03-23T11:07:08Z", "copyright": "The data included in this document is from www.openstreetmap.org. The data is made available under ODbL."}, "elements": [{"type": "node", "id": 21702885, "lat": 40.3801053, "lon": -3.7486416, "tags": {"source": "yahoo_maps"}}, {"type": "node", "id": 21702889, "lat": 40.3779089, "lon": -3.7484549, "tags": {"highway": "traffic_signals", "source": "yahoo_maps", "traffic_signals": "signal"}}, {"type": "node", "id": 259640756, "lat": 40.3805285, "lon": -3.7452707}, {"type": "node", "id": 259640757, "lat": 40.3801745, "lon": -3.7459624}, {"type": "node", "id": 301831953, "lat": 40.3787444, "lon": -3.7475354}, {"type": "node", "id": 301831955, "lat": 40.3791652, "lon": -3.7470755}, {"type": "node", "id": 301831959, "lat": 40.3797683, "lon": -3.7480269}, {"type": "node", "id": 301831994, "lat": 40.3804681, "lon": -3.7474325}, {"type": "node", "id": 301831996, "lat": 40.38017, "lon": -3.7469014}, {"type": "node", "id": 301831998, "lat": 40.3806446, "lon": -3.746404}, {"type": "node", "id": 301831999, "lat": 40.3806652, "lon": -3.7463082}, {"type": "node", "id": 301832002, "lat": 40.3802045, "lon": -3.745921}, {"type": "node", "id": 301832341, "lat": 40.379432, "lon": -3.7427893}, {"type": "node", "id": 301832342, "lat": 40.3794321, "lon": -3.7430117}, {"type": "node", "id": 301832343, "lat": 40.3801123, "lon": -3.7460297}, {"type": "node", "id": 301832344, "lat": 40.3789972, "lon": -3.7472592}, {"type": "node", "id": 301832345, "lat": 40.3785074, "lon": -3.745382}, {"type": "node", "id": 301832424, "lat": 40.3790926, "lon": -3.7451521}, {"type": "node", "id": 301832427, "lat": 40.3794746, "lon": -3.7467374}, {"type": "node", "id": 301832429, "lat": 40.3795938, "lon": -3.7466071}, {"type": "node", "id": 301832432, "lat": 40.3792546, "lon": -3.7450908}, {"type": "node", "id": 301832434, "lat": 40.3798314, "lon": -3.7448268}, {"type": "node", "id": 301832435, "lat": 40.3795346, "lon": -3.7466718}, {"type": "node", "id": 301832456, "lat": 40.3796253, "lon": -3.7439334}, {"type": "node", "id": 301832461, "lat": 40.3794937, "lon": -3.7425071}, {"type": "node", "id": 301832525, "lat": 40.3783285, "lon": -3.74799}, {"type": "node", "id": 335381417, "lat": 40.3791367, "lon": -3.7449499}, {"type": "node", "id": 1420240273, "lat": 40.3807156, "lon": -3.7447907}, {"type": "node", "id": 1420240495, "lat": 40.3792752, "lon": -3.7458993}, {"type": "node", "id": 1420240543, "lat": 40.379498, "lon": -3.7476005}, {"type": "node", "id": 1420240701, "lat": 40.3786893, "lon": -3.7461411}, {"type": "node", "id": 1439704580, "lat": 40.37995, "lon": -3.7461553, "tags": {"bench": "yes", "bin": "no", "bus": "yes", "highway": "bus_stop", "lit": "yes", "name": "Colonia de la Prensa", "network": "Empresa Municipal de Transportes de Madrid", "network:short": "EMT Madrid", "network:wikidata": "Q1094755", "operator": "Empresa Municipal de Transportes de Madrid", "operator:short": "EMT Madrid", "operator:wikidata": "Q1094755", "public_transport": "platform", "ref": "350", "shelter": "yes", "source": "https://navegapormadrid.emtmadrid.es/app/", "tactile_paving": "yes", "wheelchair": "yes"}}, {"type": "node", "id": 1992840413, "lat": 40.3780346, "lon": -3.7483112, "tags": {"button_operated": "no", "crossing": "traffic_signals", "crossing:island": "no", "highway": "crossing", "tactile_paving": "yes", "traffic_signals:sound": "yes", "traffic_signals:vibration": "no"}}, {"type": "node", "id": 1992840417, "lat": 40.3785134, "lon": -3.745473}, {"type": "node", "id": 1992840419, "lat": 40.3785747, "lon": -3.7457056}, {"type": "node", "id": 1992840422, "lat": 40.3787932, "lon": -3.7465184}, {"type": "node", "id": 1992840425, "lat": 40.3788505, "lon": -3.7474195, "tags": {"button_operated": "no", "crossing": "traffic_signals", "crossing:island": "no", "highway": "crossing", "kerb": "lowered", "tactile_paving": "yes", "traffic_signals:sound": "yes", "traffic_signals:vibration": "no"}}, {"type": "node", "id": 1992840428, "lat": 40.3789645, "lon": -3.7471405, "tags": {"crossing": "uncontrolled", "crossing:markings": "zebra", "highway": "crossing", "tactile_paving": "yes"}}, {"type": "node", "id": 1992840431, "lat": 40.3791281, "lon": -3.7452229, "tags": {"crossing": "uncontrolled", "crossing:markings": "zebra", "highway": "crossing", "tactile_paving": "yes"}}, {"type": "node", "id": 1992840432, "lat": 40.3792354, "lon": -3.7471862, "tags": {"crossing": "uncontrolled", "crossing:markings": "zebra", "highway": "crossing", "tactile_paving": "yes"}}, {"type": "node", "id": 1992840433, "lat": 40.3792535, "lon": -3.7451394}, {"type": "node", "id": 1992840434, "lat": 40.3792932, "lon": -3.7459747, "tags": {"crossing": "uncontrolled", "crossing:markings": "zebra", "highway": "crossing", "tactile_paving": "yes"}}, {"type": "node", "id": 1992840437, "lat": 40.3794467, "lon": -3.7466199, "tags": {"crossing": "uncontrolled", "crossing:markings": "zebra", "highway": "crossing", "tactile_paving": "yes"}}, {"type": "node", "id": 1992840439, "lat": 40.3794561, "lon": -3.7426747}, {"type": "node", "id": 1992840441, "lat": 40.3795686, "lon": -3.7464979, "tags": {"crossing": "uncontrolled", "crossing:markings": "zebra", "highway": "crossing", "tactile_paving": "yes"}}, {"type": "node", "id": 1992840442, "lat": 40.3798122, "lon": -3.7447435, "tags": {"crossing": "uncontrolled", "crossing:island": "no", "crossing:markings": "zebra", "highway": "crossing", "tactile_paving": "yes"}}, {"type": "node", "id": 1992840443, "lat": 40.3800807, "lon": -3.7460649, "tags": {"button_operated": "no", "crossing": "traffic_signals", "crossing:island": "no", "highway": "crossing", "kerb": "lowered", "tactile_paving": "yes", "traffic_signals:sound": "yes", "traffic_signals:vibration": "no"}}, {"type": "node", "id": 1992840444, "lat": 40.3800991, "lon": -3.7458901, "tags": {"crossing": "uncontrolled", "crossing:markings": "zebra", "highway": "crossing", "tactile_paving": "yes"}}, {"type": "node", "id": 1992840445, "lat": 40.3802704, "lon": -3.745968, "tags": {"crossing": "uncontrolled", "crossing:markings": "zebra", "highway": "crossing", "tactile_paving": "yes"}}, {"type": "node", "id": 4242067407, "lat": 40.3800662, "lon": -3.7485487, "tags": {"crossing:markings": "yes", "crossing:signals": "no", "highway": "crossing", "tactile_paving": "yes"}}, {"type": "node", "id": 4315203874, "lat": 40.3800486, "lon": -3.74576}, {"type": "node", "id": 4910958633, "lat": 40.3804313, "lon": -3.7473313}, {"type": "node", "id": 4910974710, "lat": 40.3806321, "lon": -3.746224}, {"type": "node", "id": 4914833988, "lat": 40.3800441, "lon": -3.7461056, "tags": {"highway": "traffic_signals", "traffic_signals": "signal"}}, {"type": "node", "id": 5293618203, "lat": 40.3802336, "lon": -3.7470067, "tags": {"crossing": "zebra", "highway": "crossing"}}, {"type": "node", "id": 8443728418, "lat": 40.379969, "lon": -3.7461841, "tags": {"bus": "yes", "public_transport": "stop_position"}}, {"type": "node", "id": 8443728437, "lat": 40.3782274, "lon": -3.7481002, "tags": {"bus": "yes", "public_transport": "stop_position"}}, {"type": "node", "id": 8443728438, "lat": 40.378185, "lon": -3.7481477, "tags": {"bus": "yes", "public_transport": "stop_position"}}, {"type": "node", "id": 8443728439, "lat": 40.378905, "lon": -3.7473596, "tags": {"bus": "yes", "public_transport": "stop_position"}}, {"type": "node", "id": 9078799265, "lat": 40.3791497, "lon": -3.745006}, {"type": "node", "id": 9078799279, "lat": 40.3794765, "lon": -3.7425838}, {"type": "node", "id": 9078799280, "lat": 40.3795109, "lon": -3.7425993}, {"type": "node", "id": 9078799281, "lat": 40.3802117, "lon": -3.7458555}, {"type": "node", "id": 9078799282, "lat": 40.3806087, "lon": -3.7450092}, {"type": "node", "id": 9078799283, "lat": 40.3808294, "lon": -3.7445318}, {"type": "node", "id": 9078799284, "lat": 40.3811706, "lon": -3.7440008}, {"type": "node", "id": 9078799285, "lat": 40.3814239, "lon": -3.7436816}, {"type": "node", "id": 9078799286, "lat": 40.3806225, "lon": -3.7422012}, {"type": "node", "id": 9078799287, "lat": 40.380306, "lon": -3.7416012}, {"type": "node", "id": 9078799288, "lat": 40.3802488, "lon": -3.7416012}, {"type": "node", "id": 9078799289, "lat": 40.3799096, "lon": -3.7418104}, {"type": "node", "id": 9078799290, "lat": 40.3796848, "lon": -3.7419552}, {"type": "node", "id": 9078799291, "lat": 40.3796358, "lon": -3.7420491}, {"type": "node", "id": 9078799292, "lat": 40.3795398, "lon": -3.7425051}, {"type": "node", "id": 9078799293, "lat": 40.3794805, "lon": -3.7427867}, {"type": "node", "id": 9078799294, "lat": 40.3794826, "lon": -3.7429825}, {"type": "node", "id": 9078799295, "lat": 40.3798606, "lon": -3.7447552}, {"type": "node", "id": 9078799296, "lat": 40.3800853, "lon": -3.7457556}, {"type": "node", "id": 9078799297, "lat": 40.3801262, "lon": -3.7457959}, {"type": "node", "id": 9078799298, "lat": 40.3796154, "lon": -3.746445}, {"type": "node", "id": 9078799299, "lat": 40.3800322, "lon": -3.7459353}, {"type": "node", "id": 9078799300, "lat": 40.3800363, "lon": -3.7458495}, {"type": "node", "id": 9078799301, "lat": 40.3798156, "lon": -3.7448785}, {"type": "node", "id": 9078799302, "lat": 40.3797931, "lon": -3.7448678}, {"type": "node", "id": 9078799303, "lat": 40.3793068, "lon": -3.745069}, {"type": "node", "id": 9078799304, "lat": 40.3792905, "lon": -3.7451146}, {"type": "node", "id": 9078799305, "lat": 40.3793375, "lon": -3.7453694}, {"type": "node", "id": 9078799306, "lat": 40.3795439, "lon": -3.7462518}, {"type": "node", "id": 9078799307, "lat": 40.3797537, "lon": -3.7448841}, {"type": "node", "id": 9078799308, "lat": 40.3798537, "lon": -3.7447229}, {"type": "node", "id": 9078799309, "lat": 40.3801813, "lon": -3.7458342}, {"type": "node", "id": 9078799310, "lat": 40.3795094, "lon": -3.7465629}, {"type": "node", "id": 9078799311, "lat": 40.3794131, "lon": -3.7466515}, {"type": "node", "id": 9078799312, "lat": 40.3790331, "lon": -3.7470619}, {"type": "node", "id": 9078799313, "lat": 40.3790024, "lon": -3.747086}, {"type": "node", "id": 9078799314, "lat": 40.3789513, "lon": -3.7469626}, {"type": "node", "id": 9078799315, "lat": 40.3787327, "lon": -3.746158}, {"type": "node", "id": 9078799316, "lat": 40.3792272, "lon": -3.7459568}, {"type": "node", "id": 9078799317, "lat": 40.3792496, "lon": -3.7459675}, {"type": "node", "id": 9078799318, "lat": 40.379256, "lon": -3.7459942}, {"type": "node", "id": 9078799319, "lat": 40.3793659, "lon": -3.7459416}, {"type": "node", "id": 9078799321, "lat": 40.3787082, "lon": -3.7460587}, {"type": "node", "id": 9078799322, "lat": 40.3792231, "lon": -3.7458468}, {"type": "node", "id": 9078799323, "lat": 40.3790698, "lon": -3.7451843}, {"type": "node", "id": 9078799324, "lat": 40.3790331, "lon": -3.745179}, {"type": "node", "id": 9078799325, "lat": 40.3785529, "lon": -3.7453855}, {"type": "node", "id": 9078799326, "lat": 40.3785447, "lon": -3.7454391}, {"type": "node", "id": 9078799327, "lat": 40.3791933, "lon": -3.7451949}, {"type": "node", "id": 9078799328, "lat": 40.3790828, "lon": -3.7452406}, {"type": "node", "id": 9078799329, "lat": 40.3785738, "lon": -3.7453765}, {"type": "node", "id": 9078799331, "lat": 40.378763, "lon": -3.7461456}, {"type": "node", "id": 9078799332, "lat": 40.3787542, "lon": -3.7461143}, {"type": "node", "id": 9078799333, "lat": 40.3787354, "lon": -3.7460475}, {"type": "node", "id": 9078799334, "lat": 40.3792171, "lon": -3.7459233}, {"type": "node", "id": 9078799335, "lat": 40.3791966, "lon": -3.7458577}, {"type": "node", "id": 9078799336, "lat": 40.3789358, "lon": -3.7471893}, {"type": "node", "id": 9078799435, "lat": 40.3798083, "lon": -3.7418757}, {"type": "node", "id": 9078799447, "lat": 40.3796085, "lon": -3.7421789}, {"type": "node", "id": 9429678706, "lat": 40.3788317, "lon": -3.7476126}, {"type": "node", "id": 9429678707, "lat": 40.3793515, "lon": -3.7484237}, {"type": "node", "id": 9429678708, "lat": 40.379698, "lon": -3.7480589}, {"type": "node", "id": 9429678709, "lat": 40.3797095, "lon": -3.7479795}, {"type": "node", "id": 9429678710, "lat": 40.3792093, "lon": -3.7472006}, {"type": "node", "id": 9429678711, "lat": 40.3788497, "lon": -3.7475676}, {"type": "node", "id": 9429678712, "lat": 40.37926, "lon": -3.7471727}, {"type": "node", "id": 9429678713, "lat": 40.37926, "lon": -3.7471384}, {"type": "node", "id": 9429678714, "lat": 40.3801704, "lon": -3.746072}, {"type": "node", "id": 9429678715, "lat": 40.3802456, "lon": -3.7459947}, {"type": "node", "id": 9429678716, "lat": 40.3805987, "lon": -3.7462822}, {"type": "node", "id": 9429708217, "lat": 40.3805921, "lon": -3.7463294}, {"type": "node", "id": 9429708218, "lat": 40.3805431, "lon": -3.7464239}, {"type": "node", "id": 9429708219, "lat": 40.3804761, "lon": -3.7465226}, {"type": "node", "id": 9429708220, "lat": 40.3795019, "lon": -3.7475482}, {"type": "node", "id": 9429708238, "lat": 40.3807754, "lon": -3.7446546}, {"type": "node", "id": 9518906179, "lat": 40.3803277, "lon": -3.7473709}, {"type": "node", "id": 9518906181, "lat": 40.3798331, "lon": -3.7481405}, {"type": "node", "id": 11013742772, "lat": 40.3802163, "lon": -3.7470215}, {"type": "node", "id": 11013742773, "lat": 40.3802638, "lon": -3.7469738}, {"type": "node", "id": 11013742774, "lat": 40.3803602, "lon": -3.7473387}, {"type": "node", "id": 11013742775, "lat": 40.3803665, "lon": -3.7472822}, {"type": "node", "id": 11013742776, "lat": 40.3801869, "lon": -3.7469746}, {"type": "node", "id": 11013742777, "lat": 40.3801375, "lon": -3.7469746}, {"type": "node", "id": 11013742778, "lat": 40.3795766, "lon": -3.747565}, {"type": "node", "id": 11013742779, "lat": 40.3795661, "lon": -3.7476505}, {"type": "node", "id": 11013742780, "lat": 40.3797511, "lon": -3.7479429}, {"type": "node", "id": 11013742781, "lat": 40.3798036, "lon": -3.7479429}, {"type": "node", "id": 11013747121, "lat": 40.380662, "lon": -3.7463503}, {"type": "way", "id": 27493600, "nodes": [21702885, 4242067407, 9518906181, 301831959, 1420240543, 1992840432, 301831955], "tags": {"cycleway:both": "no", "highway": "residential", "lit": "yes", "name": "Calle Salvador del Mundo", "oneway": "yes", "parking:both": "lane", "parking:both:orientation": "parallel", "sidewalk": "both", "source": "yahoo_maps", "surface": "asphalt"}}, {"type": "way", "id": 27493634, "nodes": [301832345, 1992840417, 1992840419, 1420240701, 1992840422, 1992840428, 301832344], "tags": {"highway": "residential", "lit": "yes", "maxspeed": "30", "maxspeed:type": "ES:zone30", "name": "Calle Jos\u00e9 C\u00e1rdenas", "oneway": "yes", "parking:both": "lane", "parking:both:orientation": "parallel", "postal_code": "28025", "sidewalk": "both", "sidewalk:both:surface": "paving_stones", "smoothness": "excellent", "source": "yahoo_maps", "surface": "paving_stones"}}, {"type": "way", "id": 27493635, "nodes": [301832432, 1992840433, 1992840441, 301832429], "tags": {"cycleway:both": "no", "highway": "residential", "lanes": "1", "lit": "yes", "name": "Calle Domingo de Alboraya", "oneway": "yes", "postal_code": "28025", "sidewalk": "both", "sidewalk:both:surface": "paving_stones", "smoothness": "excellent", "source": "yahoo_maps", "surface": "asphalt"}}, {"type": "way", "id": 27493636, "nodes": [301832435, 9078799310, 9078799319, 9078799327, 9078799265, 335381417], "tags": {"highway": "pedestrian", "lit": "yes", "name": "Calle Domingo de Alboraya", "postal_code": "28025", "smoothness": "excellent", "source": "yahoo_maps", "surface": "paving_stones"}}, {"type": "way", "id": 31261188, "nodes": [301832461, 9078799279, 1992840439, 301832341, 301832342, 301832456, 1992840442, 301832434, 4315203874, 1992840444], "tags": {"cycleway:both": "no", "highway": "residential", "lanes": "2", "lit": "yes", "maxspeed": "30", "maxspeed:type": "sign", "name": "Calle de la Patilla", "postal_code": "28025", "sidewalk": "both", "sidewalk:both:surface": "paving_stones", "smoothness": "excellent", "surface": "asphalt"}}, {"type": "way", "id": 128529471, "nodes": [301832002, 1992840445, 4910974710, 301831999, 11013747121, 301831998, 301831996, 1420240543], "tags": {"cycleway:both": "no", "highway": "residential", "lanes": "1", "lit": "yes", "name": "Calle de San Melit\u00f3n", "oneway": "yes", "sidewalk": "both", "source": "yahoo_maps", "surface": "asphalt"}}, {"type": "way", "id": 128529578, "nodes": [301832427, 1992840437, 1992840434, 1420240495, 1992840431, 301832424], "tags": {"cycleway:both": "no", "highway": "residential", "lanes": "1", "lit": "yes", "name": "Calle Domingo de Alboraya", "oneway": "yes", "postal_code": "28025", "sidewalk": "both", "sidewalk:both:surface": "paving_stones", "smoothness": "excellent", "source": "yahoo_maps", "surface": "asphalt"}}, {"type": "way", "id": 128529600, "nodes": [1420240495, 9078799334, 9078799332, 1420240701], "tags": {"cycleway:both": "no", "highway": "residential", "lit": "yes", "name": "Calle Marqu\u00e9s de Casa Jim\u00e9nez", "oneway": "yes", "sidewalk": "both", "surface": "asphalt"}}, {"type": "way", "id": 188660860, "nodes": [301832343, 1992840444], "tags": {"cycleway:right": "no", "highway": "residential", "lanes": "1", "lit": "yes", "maxspeed": "30", "maxspeed:type": "sign", "name": "Calle de la Patilla", "oneway": "yes", "sidewalk": "right", "sidewalk:right:surface": "paving_stones", "smoothness": "excellent", "surface": "asphalt"}}, {"type": "way", "id": 188660861, "nodes": [1992840444, 301832002], "tags": {"cycleway:both": "no", "highway": "residential", "lanes": "1", "lit": "yes", "maxspeed": "30", "maxspeed:type": "sign", "name": "Calle de la Patilla", "oneway": "yes", "sidewalk": "right", "sidewalk:right:surface": "paving_stones", "smoothness": "excellent", "surface": "asphalt"}}, {"type": "way", "id": 263355730, "nodes": [21702889, 1992840413, 8443728438, 8443728437, 301832525, 301831953, 1992840425, 8443728439, 301832344, 301831955, 301832427, 301832435, 301832429, 8443728418, 4914833988, 1992840443, 301832343], "tags": {"cycleway:both": "no", "highway": "primary", "lanes": "4", "lit": "yes", "maxspeed": "30", "maxspeed:type": "ES:urban", "name": "Calle de Eugenia de Montijo", "name:etymology:wikidata": "Q157130", "parking:both": "lane", "parking:both:orientation": "parallel", "postal_code": "28025", "sidewalk": "both", "sidewalk:both:surface": "paving_stones", "smoothness": "good", "source": "YWMS", "surface": "asphalt"}}, {"type": "way", "id": 499911860, "nodes": [301831996, 5293618203, 4910958633, 301831994], "tags": {"cycleway:both": "no", "highway": "residential", "lanes": "1", "lit": "yes", "maxspeed": "50", "name": "Calle de Sonseca", "oneway": "yes", "sidewalk": "both", "source": "yahoo_maps", "surface": "asphalt"}}, {"type": "way", "id": 981519307, "nodes": [9078799281, 9078799282, 1420240273, 9429708238, 9078799283, 9078799284, 9078799285, 9078799286, 9078799287, 9078799288, 9078799289, 9078799435, 9078799290, 9078799291, 9078799447, 9078799292, 9078799280, 9078799293, 9078799294, 9078799308, 9078799295, 9078799296, 9078799297, 9078799309, 9078799281], "tags": {"footway": "sidewalk", "highway": "footway", "lit": "yes", "smoothness": "good", "surface": "paving_stones"}}, {"type": "way", "id": 981519308, "nodes": [9078799298, 9078799299, 9078799300, 9078799301, 9078799302, 9078799307, 9078799303, 9078799304, 9078799305, 9078799306, 9078799298], "tags": {"footway": "sidewalk", "highway": "footway", "lit": "yes", "surface": "paving_stones"}}, {"type": "way", "id": 981519311, "nodes": [9078799299, 1992840444, 9078799309], "tags": {"footway": "crossing", "highway": "footway", "lit": "yes", "smoothness": "excellent", "surface": "asphalt"}}, {"type": "way", "id": 981519312, "nodes": [9078799298, 1992840441, 9078799310, 1992840437, 9078799311], "tags": {"footway": "crossing", "highway": "footway", "lit": "yes", "smoothness": "good", "surface": "asphalt"}}, {"type": "way", "id": 981519313, "nodes": [9078799311, 9078799312, 9078799313, 9078799314, 9078799315, 9078799331, 9078799316, 9078799317, 9078799318, 9078799311], "tags": {"footway": "sidewalk", "highway": "footway", "lit": "yes", "smoothness": "excellent", "surface": "paving_stones"}}, {"type": "way", "id": 981519314, "nodes": [9078799318, 1992840434, 9078799319], "tags": {"footway": "crossing", "highway": "footway", "lit": "yes", "smoothness": "excellent", "surface": "asphalt"}}, {"type": "way", "id": 981519316, "nodes": [9078799321, 9078799333, 9078799335, 9078799322, 9078799328, 9078799323, 9078799324, 9078799329, 9078799325, 9078799326, 9078799321], "tags": {"footway": "sidewalk", "highway": "footway", "lit": "yes", "surface": "paving_stones"}}, {"type": "way", "id": 981519320, "nodes": [9078799316, 9078799334, 9078799335], "tags": {"footway": "crossing", "highway": "footway", "lit": "yes", "surface": "asphalt"}}, {"type": "way", "id": 981519321, "nodes": [9078799336, 1992840428, 9078799313], "tags": {"footway": "crossing", "highway": "footway", "lit": "yes", "smoothness": "good", "surface": "asphalt"}}, {"type": "way", "id": 1022430112, "nodes": [9429678707, 9429678708, 9429678709, 9429678710, 9429678711, 9429678706, 9429678707], "tags": {"footway": "sidewalk", "highway": "footway", "lit": "yes", "smoothness": "excellent", "surface": "paving_stones"}}, {"type": "way", "id": 1022430113, "nodes": [9429678710, 1992840432, 9429678712], "tags": {"footway": "crossing", "highway": "footway", "lit": "yes", "smoothness": "excellent", "surface": "asphalt"}}, {"type": "way", "id": 1022430114, "nodes": [9429678712, 9429678713, 9429678714, 9429678715, 9429678716, 9429708217, 9429708218, 9429708219, 9429708220, 9429678712], "tags": {"footway": "sidewalk", "highway": "footway", "lit": "yes", "smoothness": "excellent", "surface": "paving_stones"}}, {"type": "way", "id": 1112870107, "nodes": [301832343, 259640757, 301832002, 259640756], "tags": {"cycleway:both": "no", "highway": "primary", "lanes": "2", "lit": "yes", "maxspeed": "30", "maxspeed:type": "ES:urban", "name": "Calle de Eugenia de Montijo", "name:etymology:wikidata": "Q157130", "parking:both": "lane", "parking:both:orientation": "parallel", "postal_code": "28025", "sidewalk": "both", "sidewalk:both:surface": "paving_stones", "smoothness": "good", "source": "YWMS", "surface": "asphalt"}}, {"type": "way", "id": 1185679060, "nodes": [11013742772, 5293618203, 11013742773], "tags": {"crossing": "uncontrolled", "crossing:markings": "yes", "footway": "crossing", "highway": "footway", "lit": "yes", "surface": "asphalt"}}, {"type": "way", "id": 1185679061, "nodes": [11013742774, 11013742775, 11013742772, 11013742776, 11013742777, 11013742778, 11013742779, 11013742780, 11013742781, 9518906179, 11013742774], "tags": {"footway": "sidewalk", "highway": "footway", "lit": "yes", "smoothness": "excellent", "surface": "paving_stones"}}]}