{"version": 0.6, "generator": "Overpass API 0.7.62.5 1bd436f1", "osm3s": {"timestamp_osm_base": "2025-03-23T16:46:47Z", "copyright": "The data included in this document is from www.openstreetmap.org. The data is made available under ODbL."}, "elements": [{"type": "node", "id": 28096046, "lat": 40.4497258, "lon": -3.6968064}, {"type": "node", "id": 28096047, "lat": 40.4495373, "lon": -3.6968259}, {"type": "node", "id": 28096048, "lat": 40.4495163, "lon": -3.6959282}, {"type": "node", "id": 28096049, "lat": 40.4492417, "lon": -3.6968565}, {"type": "node", "id": 28096050, "lat": 40.4493339, "lon": -3.6983677}, {"type": "node", "id": 81466846, "lat": 40.449229, "lon": -3.6952864}, {"type": "node", "id": 82499214, "lat": 40.4487819, "lon": -3.6969042}, {"type": "node", "id": 98746257, "lat": 40.4498186, "lon": -3.6983304}, {"type": "node", "id": 98746807, "lat": 40.4465851, "lon": -3.6971318}, {"type": "node", "id": 98746809, "lat": 40.4480236, "lon": -3.6969828, "tags": {"highway": "traffic_signals", "traffic_signals": "signal"}}, {"type": "node", "id": 98746810, "lat": 40.4493211, "lon": -3.6968483}, {"type": "node", "id": 98746811, "lat": 40.4508961, "lon": -3.6966851, "tags": {"highway": "traffic_signals", "traffic_signals": "signal"}}, {"type": "node", "id": 1654250238, "lat": 40.4466962, "lon": -3.6971203, "tags": {"crossing": "traffic_signals", "highway": "crossing", "tactile_paving": "yes"}}, {"type": "node", "id": 2533387853, "lat": 40.4522562, "lon": -3.6965601, "tags": {"crossing": "traffic_signals", "highway": "crossing", "tactile_paving": "yes"}}, {"type": "node", "id": 3221366173, "lat": 40.4495645, "lon": -3.6966304}, {"type": "node", "id": 3221366174, "lat": 40.4495879, "lon": -3.6959223}, {"type": "node", "id": 3221366175, "lat": 40.4496309, "lon": -3.6966175}, {"type": "node", "id": 4439143647, "lat": 40.4481874, "lon": -3.6969676, "tags": {"check_date:tactile_paving": "2023-07-07", "crossing": "zebra", "highway": "crossing", "tactile_paving": "yes"}}, {"type": "node", "id": 4990990038, "lat": 40.449327, "lon": -3.6982553, "tags": {"crossing": "uncontrolled", "highway": "crossing", "kerb": "lowered", "tactile_paving": "yes"}}, {"type": "node", "id": 4990990039, "lat": 40.4498118, "lon": -3.6982187, "tags": {"crossing": "uncontrolled", "highway": "crossing", "kerb": "lowered", "tactile_paving": "yes"}}, {"type": "node", "id": 8427069645, "lat": 40.4489369, "lon": -3.696888, "tags": {"bus": "yes", "public_transport": "stop_position"}}, {"type": "node", "id": 8427069646, "lat": 40.4476773, "lon": -3.6970166, "tags": {"bus": "yes", "public_transport": "stop_position"}}, {"type": "node", "id": 8427069654, "lat": 40.4519787, "lon": -3.6965706, "tags": {"bus": "yes", "public_transport": "stop_position"}}, {"type": "node", "id": 12022948917, "lat": 40.4466658, "lon": -3.6971235, "tags": {"highway": "traffic_signals"}}, {"type": "way", "id": 11072515, "nodes": [28096050, 4990990038, 28096049], "tags": {"bicycle": "yes", "bicycle:source": "enbicipormadrid", "highway": "residential", "lane_markings": "no", "lit": "yes", "name": "Calle de la Bas\u00edlica", "oneway": "yes", "source": "survey", "surface": "asphalt"}}, {"type": "way", "id": 11072569, "nodes": [98746807, 12022948917, 1654250238, 8427069646, 98746809, 4439143647, 82499214, 8427069645, 28096049, 98746810, 28096047, 28096046, 98746811, 8427069654, 2533387853], "tags": {"bicycle": "yes", "bicycle:source": "enbicipormadrid", "highway": "residential", "lanes": "2", "lit": "yes", "maxspeed": "50", "name": "Calle de Edgar Neville", "old_name": "Calle del General Moscard\u00f3", "oneway": "yes", "source": "survey", "surface": "asphalt"}}, {"type": "way", "id": 11074170, "nodes": [28096047, 3221366173, 28096048], "tags": {"highway": "residential", "lanes": "2", "lit": "yes", "name": "Calle de la Bas\u00edlica", "oneway": "yes", "surface": "asphalt"}}, {"type": "way", "id": 11074195, "nodes": [28096046, 4990990039, 98746257], "tags": {"highway": "residential", "lit": "yes", "name": "Calle de la Bas\u00edlica", "oneway": "yes", "source": "survey"}}, {"type": "way", "id": 11074205, "nodes": [98746810, 81466846], "tags": {"bicycle": "yes", "bicycle:source": "enbicipormadrid", "highway": "residential", "lanes": "2", "lit": "yes", "maxspeed": "50", "name": "Calle de la Bas\u00edlica", "oneway": "yes", "source": "survey", "surface": "asphalt"}}, {"type": "way", "id": 316018401, "nodes": [3221366174, 3221366175, 28096046], "tags": {"highway": "residential", "lanes": "2", "lit": "yes", "name": "Calle de la Bas\u00edlica", "oneway": "yes", "surface": "asphalt"}}]}