{"version": 0.6, "generator": "Overpass API 0.7.62.5 1bd436f1", "osm3s": {"timestamp_osm_base": "2025-03-23T13:02:11Z", "copyright": "The data included in this document is from www.openstreetmap.org. The data is made available under ODbL."}, "elements": [{"type": "node", "id": 255520692, "lat": 40.4138007, "lon": -3.7271561}, {"type": "node", "id": 265978730, "lat": 40.4073163, "lon": -3.7299976}, {"type": "node", "id": 265978731, "lat": 40.4081158, "lon": -3.7295717}, {"type": "node", "id": 265978732, "lat": 40.4086786, "lon": -3.7291075}, {"type": "node", "id": 265978733, "lat": 40.4091909, "lon": -3.728537, "tags": {"bus": "yes", "public_transport": "stop_position"}}, {"type": "node", "id": 265978734, "lat": 40.4102933, "lon": -3.7272647, "tags": {"button_operated": "no", "crossing": "traffic_signals", "crossing:markings": "dots", "highway": "traffic_signals", "tactile_paving": "yes", "traffic_signals:sound": "yes", "traffic_signals:vibration": "no"}}, {"type": "node", "id": 265978735, "lat": 40.4108563, "lon": -3.7266741}, {"type": "node", "id": 265978736, "lat": 40.4109598, "lon": -3.7266325}, {"type": "node", "id": 265978737, "lat": 40.4111678, "lon": -3.7266171}, {"type": "node", "id": 265978743, "lat": 40.4083463, "lon": -3.7295116}, {"type": "node", "id": 265978744, "lat": 40.4087706, "lon": -3.7291317}, {"type": "node", "id": 265978745, "lat": 40.4108408, "lon": -3.7267835}, {"type": "node", "id": 265978746, "lat": 40.4109543, "lon": -3.7267314}, {"type": "node", "id": 265978747, "lat": 40.4110672, "lon": -3.7267025}, {"type": "node", "id": 265978748, "lat": 40.4111601, "lon": -3.7267051}, {"type": "node", "id": 305396623, "lat": 40.4125485, "lon": -3.7269019}, {"type": "node", "id": 305396629, "lat": 40.4132625, "lon": -3.7270521}, {"type": "node", "id": 305396650, "lat": 40.4121804, "lon": -3.7268244}, {"type": "node", "id": 305396657, "lat": 40.4117124, "lon": -3.7267218}, {"type": "node", "id": 305396667, "lat": 40.4107753, "lon": -3.7267501}, {"type": "node", "id": 305396671, "lat": 40.4102296, "lon": -3.7273424}, {"type": "node", "id": 305396673, "lat": 40.4116975, "lon": -3.726822}, {"type": "node", "id": 305396688, "lat": 40.4088834, "lon": -3.7290039}, {"type": "node", "id": 305396739, "lat": 40.410277, "lon": -3.7274186}, {"type": "node", "id": 305396766, "lat": 40.4129054, "lon": -3.726976}, {"type": "node", "id": 305757309, "lat": 40.4121715, "lon": -3.7269156}, {"type": "node", "id": 305757313, "lat": 40.4125361, "lon": -3.7269911}, {"type": "node", "id": 335392042, "lat": 40.4083105, "lon": -3.7294348}, {"type": "node", "id": 335392044, "lat": 40.4090818, "lon": -3.7286651}, {"type": "node", "id": 341473881, "lat": 40.4110795, "lon": -3.7266114}, {"type": "node", "id": 341475616, "lat": 40.4092823, "lon": -3.7289673}, {"type": "node", "id": 341475765, "lat": 40.4092446, "lon": -3.7294488}, {"type": "node", "id": 346650025, "lat": 40.4083729, "lon": -3.7293793, "tags": {"button_operated": "no", "crossing": "traffic_signals", "crossing:markings": "dots", "highway": "crossing", "tactile_paving": "yes", "traffic_signals:sound": "yes", "traffic_signals:vibration": "no"}}, {"type": "node", "id": 348158141, "lat": 40.4106638, "lon": -3.7291249}, {"type": "node", "id": 348158157, "lat": 40.4103895, "lon": -3.7290957}, {"type": "node", "id": 348158325, "lat": 40.4101091, "lon": -3.7290617}, {"type": "node", "id": 348158343, "lat": 40.4098142, "lon": -3.7295004}, {"type": "node", "id": 348158347, "lat": 40.409836, "lon": -3.7290347}, {"type": "node", "id": 348158399, "lat": 40.4095221, "lon": -3.7294765}, {"type": "node", "id": 348158400, "lat": 40.4095573, "lon": -3.7289969}, {"type": "node", "id": 348158922, "lat": 40.4108405, "lon": -3.7286652}, {"type": "node", "id": 348159078, "lat": 40.4103117, "lon": -3.7285544}, {"type": "node", "id": 348159081, "lat": 40.4101433, "lon": -3.7286122}, {"type": "node", "id": 348159083, "lat": 40.4097016, "lon": -3.7285913}, {"type": "node", "id": 348159085, "lat": 40.4095842, "lon": -3.728207}, {"type": "node", "id": 348160174, "lat": 40.4100814, "lon": -3.7271412}, {"type": "node", "id": 348160175, "lat": 40.4089354, "lon": -3.7284373}, {"type": "node", "id": 348160340, "lat": 40.4094456, "lon": -3.728238}, {"type": "node", "id": 348160442, "lat": 40.4095482, "lon": -3.728116}, {"type": "node", "id": 348160678, "lat": 40.4101008, "lon": -3.7276344}, {"type": "node", "id": 348160679, "lat": 40.4100301, "lon": -3.7275649}, {"type": "node", "id": 364197510, "lat": 40.407907, "lon": -3.7296917}, {"type": "node", "id": 750088545, "lat": 40.4097523, "lon": -3.7268201}, {"type": "node", "id": 750088547, "lat": 40.4094119, "lon": -3.7269083}, {"type": "node", "id": 750088549, "lat": 40.4096902, "lon": -3.7265164}, {"type": "node", "id": 750088553, "lat": 40.4097713, "lon": -3.7267012}, {"type": "node", "id": 750088554, "lat": 40.4091537, "lon": -3.7272373}, {"type": "node", "id": 750118902, "lat": 40.4094912, "lon": -3.728311}, {"type": "node", "id": 750118984, "lat": 40.4093198, "lon": -3.7280363}, {"type": "node", "id": 750119048, "lat": 40.409894, "lon": -3.7278608}, {"type": "node", "id": 750119094, "lat": 40.4098347, "lon": -3.7277872}, {"type": "node", "id": 750119277, "lat": 40.409705, "lon": -3.7275845}, {"type": "node", "id": 750119302, "lat": 40.4097054, "lon": -3.7265395}, {"type": "node", "id": 750127955, "lat": 40.4095922, "lon": -3.7274194}, {"type": "node", "id": 750127957, "lat": 40.4100663, "lon": -3.7271605}, {"type": "node", "id": 750127962, "lat": 40.4105305, "lon": -3.726988}, {"type": "node", "id": 750127965, "lat": 40.409231, "lon": -3.7278377}, {"type": "node", "id": 750127967, "lat": 40.4099586, "lon": -3.7269951}, {"type": "node", "id": 750127968, "lat": 40.4093325, "lon": -3.727279}, {"type": "node", "id": 750127969, "lat": 40.4093471, "lon": -3.7280042, "tags": {"crossing": "uncontrolled", "crossing:markings": "zebra", "highway": "crossing", "tactile_paving": "yes"}}, {"type": "node", "id": 757493542, "lat": 40.4083435, "lon": -3.7281712}, {"type": "node", "id": 757493576, "lat": 40.4081562, "lon": -3.7276353}, {"type": "node", "id": 757493587, "lat": 40.4075692, "lon": -3.7298718}, {"type": "node", "id": 757493590, "lat": 40.408045, "lon": -3.7276993}, {"type": "node", "id": 757493605, "lat": 40.4080465, "lon": -3.7282233}, {"type": "node", "id": 757493608, "lat": 40.4085789, "lon": -3.7285453}, {"type": "node", "id": 757493618, "lat": 40.4078526, "lon": -3.7286914}, {"type": "node", "id": 757493627, "lat": 40.4083108, "lon": -3.7277678}, {"type": "node", "id": 757493632, "lat": 40.4078817, "lon": -3.7291193}, {"type": "node", "id": 757493643, "lat": 40.4082234, "lon": -3.7276489}, {"type": "node", "id": 757493647, "lat": 40.407854, "lon": -3.7292906}, {"type": "node", "id": 757493656, "lat": 40.4079083, "lon": -3.7295093}, {"type": "node", "id": 757493678, "lat": 40.4085538, "lon": -3.7285091}, {"type": "node", "id": 871308650, "lat": 40.4084082, "lon": -3.729457, "tags": {"button_operated": "no", "crossing": "traffic_signals", "crossing:markings": "dots", "highway": "crossing", "tactile_paving": "yes", "traffic_signals:sound": "yes", "traffic_signals:vibration": "no"}}, {"type": "node", "id": 871308651, "lat": 40.4088372, "lon": -3.7289387}, {"type": "node", "id": 871308657, "lat": 40.4097091, "lon": -3.7265927}, {"type": "node", "id": 871308664, "lat": 40.4079527, "lon": -3.7296646}, {"type": "node", "id": 871308665, "lat": 40.4097759, "lon": -3.7267616}, {"type": "node", "id": 1315593545, "lat": 40.4088265, "lon": -3.7292081, "tags": {"check_date:crossing": "2021-10-14", "crossing": "uncontrolled", "highway": "crossing", "tactile_paving": "yes"}}, {"type": "node", "id": 1315593549, "lat": 40.4088803, "lon": -3.7291725, "tags": {"check_date:crossing": "2021-10-14", "crossing": "uncontrolled", "highway": "crossing", "tactile_paving": "yes"}}, {"type": "node", "id": 1315593556, "lat": 40.4100551, "lon": -3.7286291}, {"type": "node", "id": 1315593562, "lat": 40.4102608, "lon": -3.7285598}, {"type": "node", "id": 1315593567, "lat": 40.4096491, "lon": -3.7285425}, {"type": "node", "id": 1315593570, "lat": 40.4096387, "lon": -3.7283375}, {"type": "node", "id": 1315593597, "lat": 40.4088814, "lon": -3.7293023}, {"type": "node", "id": 1439703337, "lat": 40.4093317, "lon": -3.7283062, "tags": {"bench": "yes", "bin": "no", "bus": "yes", "highway": "bus_stop", "lit": "yes", "name": "Caramuel-Do\u00f1a Menc\u00eda", "operator": "EMT Madrid", "public_transport": "platform", "ref": "1458", "shelter": "yes", "source": "https://navegapormadrid.emtmadrid.es/app/", "tactile_paving": "yes"}}, {"type": "node", "id": 1439703338, "lat": 40.4094458, "lon": -3.728421, "tags": {"bench": "yes", "bin": "no", "bus": "yes", "highway": "bus_stop", "lit": "yes", "name": "Caramuel-Do\u00f1a Menc\u00eda", "operator": "EMT Madrid", "public_transport": "platform", "ref": "1457", "shelter": "yes", "source": "https://navegapormadrid.emtmadrid.es/app/", "tactile_paving": "yes"}}, {"type": "node", "id": 1481724099, "lat": 40.4078797, "lon": -3.7293943}, {"type": "node", "id": 1481724102, "lat": 40.4080181, "lon": -3.7278225}, {"type": "node", "id": 1481724109, "lat": 40.4082442, "lon": -3.7294836, "tags": {"highway": "traffic_signals"}}, {"type": "node", "id": 1481724114, "lat": 40.4086996, "lon": -3.7287189}, {"type": "node", "id": 1481724132, "lat": 40.4103403, "lon": -3.7273456, "tags": {"button_operated": "no", "crossing": "traffic_signals", "crossing:markings": "dots", "highway": "traffic_signals", "tactile_paving": "yes", "traffic_signals:sound": "yes", "traffic_signals:vibration": "no"}}, {"type": "node", "id": 1614406355, "lat": 40.4117757, "lon": -3.7268387, "tags": {"crossing": "uncontrolled", "crossing:markings": "zebra", "highway": "crossing", "kerb": "lowered", "tactile_paving": "yes"}}, {"type": "node", "id": 1614406357, "lat": 40.4117818, "lon": -3.7267394, "tags": {"crossing": "uncontrolled", "crossing:markings": "zebra", "highway": "crossing", "kerb": "lowered", "tactile_paving": "yes"}}, {"type": "node", "id": 1614406428, "lat": 40.4136297, "lon": -3.7271291, "tags": {"crossing": "traffic_signals", "highway": "crossing"}}, {"type": "node", "id": 3802745975, "lat": 40.4090607, "lon": -3.7277836}, {"type": "node", "id": 3802745976, "lat": 40.409254, "lon": -3.7280613}, {"type": "node", "id": 3802745977, "lat": 40.4092861, "lon": -3.7288271}, {"type": "node", "id": 3802745978, "lat": 40.4093484, "lon": -3.7287342}, {"type": "node", "id": 3802745979, "lat": 40.4093591, "lon": -3.7288422}, {"type": "node", "id": 4544929575, "lat": 40.4098609, "lon": -3.727897}, {"type": "node", "id": 5879150004, "lat": 40.4078735, "lon": -3.7286172}, {"type": "node", "id": 5879150005, "lat": 40.4080405, "lon": -3.7282986}, {"type": "node", "id": 5879150006, "lat": 40.4079842, "lon": -3.7283781}, {"type": "node", "id": 5879150007, "lat": 40.4078962, "lon": -3.728537}, {"type": "node", "id": 5879150008, "lat": 40.4078608, "lon": -3.7288335}, {"type": "node", "id": 5879150009, "lat": 40.4078854, "lon": -3.7289838}, {"type": "node", "id": 5999813750, "lat": 40.4087061, "lon": -3.7278973}, {"type": "node", "id": 5999813751, "lat": 40.40833, "lon": -3.7280042}, {"type": "node", "id": 5999813752, "lat": 40.4085179, "lon": -3.7279598}, {"type": "node", "id": 5999813753, "lat": 40.4085733, "lon": -3.7279279}, {"type": "node", "id": 5999813754, "lat": 40.4086224, "lon": -3.72791}, {"type": "node", "id": 5999813755, "lat": 40.4087941, "lon": -3.7278642}, {"type": "node", "id": 8007022942, "lat": 40.4085276, "lon": -3.72925}, {"type": "node", "id": 8441812631, "lat": 40.409141, "lon": -3.7287149, "tags": {"bus": "yes", "public_transport": "stop_position"}}, {"type": "node", "id": 8441812632, "lat": 40.4131361, "lon": -3.7270251, "tags": {"bus": "yes", "public_transport": "stop_position"}}, {"type": "node", "id": 8441812638, "lat": 40.4104959, "lon": -3.7271736, "tags": {"bus": "yes", "public_transport": "stop_position"}}, {"type": "node", "id": 8441812639, "lat": 40.4104312, "lon": -3.7271031, "tags": {"bus": "yes", "public_transport": "stop_position"}}, {"type": "node", "id": 8721505300, "lat": 40.4092033, "lon": -3.7278684}, {"type": "node", "id": 8721505301, "lat": 40.4090244, "lon": -3.7275946}, {"type": "node", "id": 8721505302, "lat": 40.4095192, "lon": -3.7270749}, {"type": "node", "id": 8721505303, "lat": 40.4091673, "lon": -3.7278166}, {"type": "node", "id": 8721505304, "lat": 40.4092352, "lon": -3.7273881}, {"type": "node", "id": 9087716742, "lat": 40.4094091, "lon": -3.7287854, "tags": {"noexit": "yes"}}, {"type": "node", "id": 9087716743, "lat": 40.4093732, "lon": -3.7284471}, {"type": "node", "id": 9226751279, "lat": 40.4101464, "lon": -3.7283394}, {"type": "node", "id": 9226751280, "lat": 40.4098977, "lon": -3.7282913}, {"type": "node", "id": 12494008048, "lat": 40.4128397, "lon": -3.726963, "tags": {"crossing": "uncontrolled", "highway": "crossing"}}, {"type": "node", "id": 12494008049, "lat": 40.4128284, "lon": -3.7269608}, {"type": "node", "id": 12494008055, "lat": 40.4107814, "lon": -3.7286528, "tags": {"crossing": "uncontrolled", "crossing:markings": "yes", "highway": "crossing"}}, {"type": "way", "id": 27813559, "nodes": [305396688, 1315593549, 1315593597], "tags": {"cycleway:both": "no", "highway": "residential", "lanes": "1", "lit": "yes", "name": "Calle de Calatayud", "oneway": "yes", "sidewalk": "both", "smoothness": "excellent", "surface": "asphalt"}}, {"type": "way", "id": 31293110, "nodes": [341475765, 341475616], "tags": {"highway": "residential", "lanes": "1", "lit": "yes", "name": "Calle de Vinuesa", "oneway": "yes", "sidewalk": "both", "surface": "asphalt"}}, {"type": "way", "id": 31293134, "nodes": [348158343, 348158347], "tags": {"highway": "residential", "lanes": "1", "lit": "yes", "name": "Calle de Gij\u00f3n", "oneway": "yes", "sidewalk": "both", "surface": "asphalt"}}, {"type": "way", "id": 31293137, "nodes": [348158400, 348158399], "tags": {"highway": "residential", "lanes": "1", "lit": "yes", "name": "Calle de And\u00fajar", "oneway": "yes", "sidewalk": "both", "surface": "asphalt"}}, {"type": "way", "id": 31293198, "nodes": [348158922, 12494008055, 348159078, 1315593562, 348159081, 1315593556, 348159083, 1315593567, 1315593570, 348159085, 348160442], "tags": {"highway": "residential", "lanes": "1", "lit": "yes", "name": "Calle de Jaime Vera", "oneway": "yes", "sidewalk": "both", "surface": "asphalt"}}, {"type": "way", "id": 31293244, "nodes": [750118984, 750127969, 750119277, 750127957, 348160174], "tags": {"highway": "residential", "lanes": "1", "lit": "yes", "name": "Calle de Fuenteovejuna", "oneway": "yes", "sidewalk": "both", "surface": "asphalt"}}, {"type": "way", "id": 60320802, "nodes": [750088549, 750119302, 871308657, 750088553, 871308665, 750088545, 8721505302, 750127968, 8721505304, 8721505303, 8721505300, 750118984], "tags": {"highway": "residential", "lanes": "1", "lit": "yes", "name": "Calle de Bujalance", "oneway": "yes", "sidewalk": "right", "surface": "asphalt"}}, {"type": "way", "id": 60321334, "nodes": [750118902, 348160340, 750118984], "tags": {"cycleway:both": "no", "highway": "residential", "lanes": "1", "lit": "yes", "name": "Calle de Fuenteovejuna", "oneway": "yes", "sidewalk": "both", "surface": "asphalt"}}, {"type": "way", "id": 60321344, "nodes": [750119277, 750119094, 750119048], "tags": {"highway": "residential", "lanes": "1", "lit": "yes", "name": "Calle de Fuenteovejuna", "oneway": "yes", "sidewalk": "both", "surface": "asphalt"}}, {"type": "way", "id": 60321348, "nodes": [348160175, 335392044], "tags": {"cycleway:both": "no", "highway": "residential", "lanes": "1", "lit": "yes", "name": "Calle de Fuenteovejuna", "oneway": "yes", "sidewalk": "left", "surface": "asphalt"}}, {"type": "way", "id": 60611984, "nodes": [871308664, 757493656, 1481724099, 757493647, 757493632, 5879150009, 5879150008, 757493618, 5879150004, 5879150007, 5879150006, 5879150005, 757493605, 1481724102, 757493590, 757493576, 757493643, 757493627, 5999813751, 757493542, 757493678, 757493608, 1481724114, 871308651], "tags": {"bicycle": "yes", "highway": "footway", "surface": "compacted"}}, {"type": "way", "id": 73531594, "nodes": [265978730, 757493587, 364197510, 871308664, 265978731, 1481724109, 335392042, 346650025, 8007022942, 265978732, 871308651, 335392044, 265978733, 348160340, 348160442, 750119094, 348160679, 305396671, 265978734, 8441812639, 750127962, 305396667, 265978735, 265978736, 341473881, 265978737, 305396657, 1614406357, 305396650, 305396623, 12494008049, 12494008048, 305396766, 8441812632, 305396629, 1614406428, 255520692], "tags": {"cycleway:right": "no", "highway": "tertiary", "lanes": "1", "lit": "yes", "maxspeed": "40", "name": "Calle de Caramuel", "oneway": "yes", "parking:left": "no", "parking:right": "street_side", "parking:right:orientation": "parallel", "sidewalk": "right", "sidewalk:right:surface": "paving_stones", "smoothness": "excellent", "surface": "asphalt"}}, {"type": "way", "id": 73531595, "nodes": [750127969, 750127965], "tags": {"highway": "footway", "surface": "paving_stones"}}, {"type": "way", "id": 73531598, "nodes": [750127965, 750127955, 750127967], "tags": {"highway": "footway", "surface": "paving_stones"}}, {"type": "way", "id": 116772797, "nodes": [1315593597, 1315593545, 265978744], "tags": {"cycleway:both": "no", "highway": "residential", "lanes": "1", "lit": "yes", "name": "Calle de Calatayud", "oneway": "yes", "sidewalk": "both", "smoothness": "excellent", "surface": "asphalt"}}, {"type": "way", "id": 134833927, "nodes": [1315593545, 1315593549], "tags": {"footway": "crossing", "highway": "footway", "lit": "yes", "smoothness": "excellent", "surface": "asphalt"}}, {"type": "way", "id": 261929378, "nodes": [305757313, 305757309, 1614406355, 305396673, 265978748, 265978747, 265978746, 265978745, 8441812638, 1481724132, 305396739, 348160678, 750119048, 4544929575, 348159085, 750118902, 9087716743, 8441812631, 305396688, 265978744, 871308650, 265978743], "tags": {"cycleway:right": "no", "highway": "tertiary", "lanes": "2", "lit": "yes", "maxspeed": "40", "name": "Calle de Caramuel", "oneway": "yes", "parking:left": "no", "parking:right": "street_side", "parking:right:orientation": "parallel", "sidewalk": "right", "sidewalk:right:surface": "paving_stones", "smoothness": "excellent", "surface": "asphalt"}}, {"type": "way", "id": 328889791, "nodes": [341475616, 348158400, 348158347, 348158325, 348158157, 348158141], "tags": {"highway": "residential", "lanes": "1", "lit": "yes", "name": "Calle de Do\u00f1a Menc\u00eda", "oneway": "yes", "sidewalk": "both", "surface": "asphalt"}}, {"type": "way", "id": 376896962, "nodes": [3802745976, 3802745975], "tags": {"highway": "service", "lit": "yes", "surface": "asphalt"}}, {"type": "way", "id": 376896963, "nodes": [341475616, 3802745977, 3802745979, 3802745978], "tags": {"handrail": "yes", "highway": "steps", "incline": "down", "ramp": "no", "surface": "paving_stones"}}, {"type": "way", "id": 461175597, "nodes": [750118984, 3802745976, 348160175], "tags": {"cycleway:both": "no", "highway": "residential", "lanes": "1", "lit": "yes", "name": "Calle de Fuenteovejuna", "oneway": "yes", "sidewalk": "both", "surface": "asphalt"}}, {"type": "way", "id": 636231023, "nodes": [8721505301, 5999813755, 5999813750, 5999813754, 5999813753, 5999813752, 5999813751], "tags": {"highway": "footway"}}, {"type": "way", "id": 941786929, "nodes": [750127965, 8721505300], "tags": {"highway": "footway", "surface": "asphalt"}}, {"type": "way", "id": 941786931, "nodes": [8721505303, 8721505301, 750088554, 750088547], "tags": {"highway": "residential", "lanes": "1", "lit": "yes", "name": "Calle de Bujalance", "oneway": "yes", "surface": "asphalt"}}, {"type": "way", "id": 982764821, "nodes": [9087716742, 9087716743], "tags": {"highway": "residential", "lit": "yes", "name": "Calle de Do\u00f1a Menc\u00eda", "surface": "asphalt"}}, {"type": "way", "id": 999486008, "nodes": [4544929575, 9226751280, 9226751279], "tags": {"highway": "residential", "lit": "yes", "noname": "yes", "oneway": "no", "surface": "asphalt"}}]}