{"version": 0.6, "generator": "Overpass API 0.7.62.5 1bd436f1", "osm3s": {"timestamp_osm_base": "2025-03-23T16:46:47Z", "copyright": "The data included in this document is from www.openstreetmap.org. The data is made available under ODbL."}, "elements": [{"type": "node", "id": 20960708, "lat": 40.4193533, "lon": -3.6206161}, {"type": "node", "id": 21992224, "lat": 40.4225245, "lon": -3.6187616}, {"type": "node", "id": 21993874, "lat": 40.4236087, "lon": -3.6170742}, {"type": "node", "id": 24967619, "lat": 40.420812, "lon": -3.6216778}, {"type": "node", "id": 24967629, "lat": 40.4198368, "lon": -3.6209523}, {"type": "node", "id": 24967642, "lat": 40.4215696, "lon": -3.6222147}, {"type": "node", "id": 24967644, "lat": 40.4205426, "lon": -3.6221389}, {"type": "node", "id": 24967646, "lat": 40.4204279, "lon": -3.6223995}, {"type": "node", "id": 24967647, "lat": 40.4203711, "lon": -3.6226427}, {"type": "node", "id": 24967648, "lat": 40.4203584, "lon": -3.6228317}, {"type": "node", "id": 24967650, "lat": 40.4203856, "lon": -3.6231366}, {"type": "node", "id": 24967653, "lat": 40.4204981, "lon": -3.6234618}, {"type": "node", "id": 24967655, "lat": 40.4206106, "lon": -3.6236382}, {"type": "node", "id": 24967659, "lat": 40.4207763, "lon": -3.6238212}, {"type": "node", "id": 24967662, "lat": 40.4209305, "lon": -3.6240012}, {"type": "node", "id": 24969014, "lat": 40.4224976, "lon": -3.6256957}, {"type": "node", "id": 24969041, "lat": 40.4234157, "lon": -3.6235355}, {"type": "node", "id": 351522367, "lat": 40.4212018, "lon": -3.6219408}, {"type": "node", "id": 351522607, "lat": 40.4214107, "lon": -3.6214963}, {"type": "node", "id": 351522609, "lat": 40.421558, "lon": -3.6215023}, {"type": "node", "id": 351522610, "lat": 40.4216332, "lon": -3.6214153}, {"type": "node", "id": 351522611, "lat": 40.4216411, "lon": -3.6212039}, {"type": "node", "id": 351522613, "lat": 40.4215637, "lon": -3.6211014}, {"type": "node", "id": 351522821, "lat": 40.4215115, "lon": -3.6204806}, {"type": "node", "id": 351523458, "lat": 40.4226672, "lon": -3.6230052}, {"type": "node", "id": 351524134, "lat": 40.4238541, "lon": -3.6167426}, {"type": "node", "id": 351524300, "lat": 40.4240134, "lon": -3.6165287}, {"type": "node", "id": 351524510, "lat": 40.4232739, "lon": -3.6175559}, {"type": "node", "id": 351524623, "lat": 40.4230993, "lon": -3.6178391}, {"type": "node", "id": 352653643, "lat": 40.4194545, "lon": -3.6236725}, {"type": "node", "id": 352653644, "lat": 40.4194924, "lon": -3.6234748}, {"type": "node", "id": 352653645, "lat": 40.4195907, "lon": -3.6233226}, {"type": "node", "id": 352653646, "lat": 40.4198147, "lon": -3.6229027}, {"type": "node", "id": 352653647, "lat": 40.4200515, "lon": -3.6225897}, {"type": "node", "id": 352653648, "lat": 40.4204288, "lon": -3.6219775}, {"type": "node", "id": 352653649, "lat": 40.4206592, "lon": -3.6215705}, {"type": "node", "id": 352653651, "lat": 40.4198582, "lon": -3.6228313}, {"type": "node", "id": 352653838, "lat": 40.4219785, "lon": -3.6251555}, {"type": "node", "id": 352653842, "lat": 40.4205652, "lon": -3.6235811}, {"type": "node", "id": 1439700089, "lat": 40.4205401, "lon": -3.6219022, "tags": {"bus": "yes", "highway": "bus_stop", "name": "Arcos de Jal\u00f3n-San Rom\u00e1n del Valle", "operator": "EMT Madrid", "public_transport": "platform", "ref": "1202", "source": "https://navegapormadrid.emtmadrid.es/app/"}}, {"type": "node", "id": 1439700091, "lat": 40.420774, "lon": -3.6219633, "tags": {"bus": "yes", "highway": "bus_stop", "name": "Arcos de Jal\u00f3n-San Rom\u00e1n del Valle", "operator": "EMT Madrid", "public_transport": "platform", "ref": "1203", "source": "https://navegapormadrid.emtmadrid.es/app/"}}, {"type": "node", "id": 1594908136, "lat": 40.4242002, "lon": -3.6162792}, {"type": "node", "id": 1594908160, "lat": 40.424609, "lon": -3.6157844}, {"type": "node", "id": 1594978069, "lat": 40.4243773, "lon": -3.6160647}, {"type": "node", "id": 1597694433, "lat": 40.4227858, "lon": -3.6183208}, {"type": "node", "id": 1597694475, "lat": 40.4226383, "lon": -3.6185773}, {"type": "node", "id": 1597694519, "lat": 40.4228151, "lon": -3.6182725}, {"type": "node", "id": 1597746817, "lat": 40.4235105, "lon": -3.6172109}, {"type": "node", "id": 1607019046, "lat": 40.4212174, "lon": -3.620984}, {"type": "node", "id": 1607019069, "lat": 40.4213375, "lon": -3.6213973}, {"type": "node", "id": 1607019070, "lat": 40.421322, "lon": -3.6213304}, {"type": "node", "id": 1607019072, "lat": 40.4213681, "lon": -3.6214545}, {"type": "node", "id": 1607019074, "lat": 40.4213731, "lon": -3.6211392}, {"type": "node", "id": 1607019076, "lat": 40.421406, "lon": -3.6211072}, {"type": "node", "id": 1607019077, "lat": 40.4214438, "lon": -3.6210866}, {"type": "node", "id": 1607019081, "lat": 40.4214408, "lon": -3.6206043}, {"type": "node", "id": 1607019083, "lat": 40.4214843, "lon": -3.6210786}, {"type": "node", "id": 1607019086, "lat": 40.4215092, "lon": -3.62152}, {"type": "node", "id": 1607019105, "lat": 40.4215251, "lon": -3.6210836}, {"type": "node", "id": 1607019108, "lat": 40.4216006, "lon": -3.6214663}, {"type": "node", "id": 1607019112, "lat": 40.4216089, "lon": -3.6211441}, {"type": "node", "id": 1607019113, "lat": 40.4216566, "lon": -3.6212742}, {"type": "node", "id": 1607019223, "lat": 40.4236954, "lon": -3.6169556}, {"type": "node", "id": 1609220181, "lat": 40.423183, "lon": -3.6233768}, {"type": "node", "id": 1609220191, "lat": 40.4221448, "lon": -3.6226289}, {"type": "node", "id": 1810994389, "lat": 40.4204449, "lon": -3.6233334}, {"type": "node", "id": 1810994391, "lat": 40.4203649, "lon": -3.6229883}, {"type": "node", "id": 2654527090, "lat": 40.423335, "lon": -3.6174698}, {"type": "node", "id": 2788767395, "lat": 40.4202847, "lon": -3.6217455, "tags": {"barrier": "gate"}}, {"type": "node", "id": 3431999162, "lat": 40.4203076, "lon": -3.6221587}, {"type": "node", "id": 3588244550, "lat": 40.4213456, "lon": -3.6244599}, {"type": "node", "id": 3588244553, "lat": 40.4223682, "lon": -3.6255762}, {"type": "node", "id": 3679896049, "lat": 40.4210762, "lon": -3.6241647}, {"type": "node", "id": 3703778970, "lat": 40.4232947, "lon": -3.6234531, "tags": {"crossing": "zebra", "crossing:island": "no", "highway": "crossing"}}, {"type": "node", "id": 4272234292, "lat": 40.4195091, "lon": -3.6207301, "tags": {"crossing": "traffic_signals", "highway": "traffic_signals"}}, {"type": "node", "id": 4938091905, "lat": 40.4195057, "lon": -3.6208623}, {"type": "node", "id": 4938091908, "lat": 40.4194445, "lon": -3.6208542}, {"type": "node", "id": 4938091912, "lat": 40.4205033, "lon": -3.6215738}, {"type": "node", "id": 8316786009, "lat": 40.4192649, "lon": -3.6242753}, {"type": "node", "id": 8346212861, "lat": 40.4194955, "lon": -3.6207202, "tags": {"highway": "crossing"}}, {"type": "node", "id": 8762943413, "lat": 40.4236535, "lon": -3.6170129}, {"type": "node", "id": 8779208753, "lat": 40.4227488, "lon": -3.618396, "tags": {"bus": "yes", "public_transport": "stop_position"}}, {"type": "node", "id": 8779208754, "lat": 40.4206372, "lon": -3.6219743, "tags": {"bus": "yes", "public_transport": "stop_position"}}, {"type": "node", "id": 8779208758, "lat": 40.4244982, "lon": -3.6159148, "tags": {"bus": "yes", "public_transport": "stop_position"}}, {"type": "node", "id": 8779208759, "lat": 40.4206823, "lon": -3.6218983, "tags": {"bus": "yes", "public_transport": "stop_position"}}, {"type": "node", "id": 8779208760, "lat": 40.4204781, "lon": -3.6222627}, {"type": "node", "id": 8779208761, "lat": 40.4206982, "lon": -3.6218696}, {"type": "node", "id": 8779208763, "lat": 40.4244313, "lon": -3.615998, "tags": {"bus": "yes", "public_transport": "stop_position"}}, {"type": "node", "id": 8779208767, "lat": 40.422087, "lon": -3.6252726, "tags": {"bus": "yes", "public_transport": "stop_position"}}, {"type": "node", "id": 8779208768, "lat": 40.4226685, "lon": -3.618528, "tags": {"bus": "yes", "public_transport": "stop_position"}}, {"type": "node", "id": 11169638024, "lat": 40.4247022, "lon": -3.6156802}, {"type": "node", "id": 11964573723, "lat": 40.4216539, "lon": -3.6213473}, {"type": "node", "id": 11964573724, "lat": 40.4214586, "lon": -3.621518}, {"type": "node", "id": 11964573725, "lat": 40.4213231, "lon": -3.6212606}, {"type": "node", "id": 11964573726, "lat": 40.4213407, "lon": -3.6211947}, {"type": "node", "id": 12313923608, "lat": 40.4205435, "lon": -3.6214836}, {"type": "node", "id": 12313923609, "lat": 40.4204341, "lon": -3.6217292}, {"type": "node", "id": 12313923610, "lat": 40.4203993, "lon": -3.6217654}, {"type": "node", "id": 12313923611, "lat": 40.4203636, "lon": -3.6217681}, {"type": "node", "id": 12313923612, "lat": 40.420333, "lon": -3.6217681}, {"type": "node", "id": 12313923613, "lat": 40.4200461, "lon": -3.6215696}, {"type": "way", "id": 31467571, "nodes": [351522367, 351522607], "tags": {"highway": "footway"}}, {"type": "way", "id": 31508531, "nodes": [8316786009, 352653643, 352653644, 352653645, 352653646, 352653651, 352653647, 3431999162, 352653648, 352653649], "tags": {"highway": "footway"}}, {"type": "way", "id": 147132684, "nodes": [20960708, 8346212861, 4272234292, 24967629, 12313923608, 352653649, 24967619, 351522367, 24967642, 1609220191, 351523458, 1609220181, 3703778970, 24969041], "tags": {"highway": "residential", "name": "Calle de San Rom\u00e1n del Valle", "postal_code": "28037"}}, {"type": "way", "id": 147488374, "nodes": [351522613, 1607019112, 351522611, 1607019113, 11964573723, 351522610, 1607019108, 351522609, 1607019086, 11964573724, 351522607, 1607019072, 1607019069, 1607019070, 11964573725, 11964573726, 1607019074, 1607019076, 1607019077, 1607019083, 1607019105, 351522613], "tags": {"highway": "footway", "surface": "paving_stones"}}, {"type": "way", "id": 147488384, "nodes": [1607019074, 1607019046], "tags": {"highway": "footway", "surface": "paving_stones"}}, {"type": "way", "id": 335732443, "nodes": [11169638024, 1594908160, 8779208758, 8779208763, 1594978069, 1594908136, 351524300, 351524134, 1607019223, 8762943413, 21993874, 1597746817, 2654527090, 351524510, 351524623, 1597694519, 1597694433, 8779208753, 8779208768, 1597694475, 21992224, 351522821, 1607019081, 1607019046, 24967619, 8779208761, 8779208759, 8779208754, 24967644, 8779208760, 24967646, 24967647, 24967648, 1810994391, 24967650, 1810994389, 24967653, 352653842, 24967655, 24967659, 24967662, 3679896049, 3588244550, 352653838, 8779208767, 3588244553, 24969014], "tags": {"highway": "tertiary", "maxspeed": "30", "name": "Calle de Arcos de Jal\u00f3n", "oneway": "no", "postal_code": "28037"}}, {"type": "way", "id": 503519892, "nodes": [4938091908, 4938091905, 4938091912], "tags": {"highway": "footway"}}, {"type": "way", "id": 1330857945, "nodes": [12313923613, 2788767395], "tags": {"highway": "service"}}, {"type": "way", "id": 1330857946, "nodes": [2788767395, 12313923612, 12313923611, 12313923610, 12313923609, 4938091912, 12313923608], "tags": {"highway": "service"}}]}