{"version": 0.6, "generator": "Overpass API 0.7.62.5 1bd436f1", "osm3s": {"timestamp_osm_base": "2025-03-23T13:01:10Z", "copyright": "The data included in this document is from www.openstreetmap.org. The data is made available under ODbL."}, "elements": [{"type": "node", "id": 26282204, "lat": 40.3519237, "lon": -3.693123}, {"type": "node", "id": 26282205, "lat": 40.3519657, "lon": -3.6929601}, {"type": "node", "id": 26282212, "lat": 40.3506625, "lon": -3.6931772}, {"type": "node", "id": 248790605, "lat": 40.3524228, "lon": -3.6931203}, {"type": "node", "id": 248790764, "lat": 40.3517309, "lon": -3.6934544, "tags": {"highway": "turning_circle"}}, {"type": "node", "id": 248795115, "lat": 40.3514831, "lon": -3.6933798}, {"type": "node", "id": 248795116, "lat": 40.3504011, "lon": -3.6967299}, {"type": "node", "id": 248795163, "lat": 40.3518558, "lon": -3.6931232}, {"type": "node", "id": 248795318, "lat": 40.3512134, "lon": -3.6937854, "tags": {"highway": "crossing"}}, {"type": "node", "id": 248795319, "lat": 40.35106, "lon": -3.6931578, "tags": {"highway": "traffic_signals"}}, {"type": "node", "id": 306257967, "lat": 40.3507464, "lon": -3.6956849}, {"type": "node", "id": 306258325, "lat": 40.349673, "lon": -3.6931696}, {"type": "node", "id": 306258360, "lat": 40.349728, "lon": -3.6935582}, {"type": "node", "id": 306258499, "lat": 40.3505633, "lon": -3.6962652}, {"type": "node", "id": 316433492, "lat": 40.3527313, "lon": -3.6939044, "tags": {"source": "PNOA", "source:date": "2009"}}, {"type": "node", "id": 316433575, "lat": 40.3514927, "lon": -3.6938545}, {"type": "node", "id": 316433576, "lat": 40.3514499, "lon": -3.6943531}, {"type": "node", "id": 316433577, "lat": 40.3527176, "lon": -3.6943974, "tags": {"source": "PNOA", "source:date": "2009"}}, {"type": "node", "id": 316433654, "lat": 40.3509866, "lon": -3.6948862}, {"type": "node", "id": 316434210, "lat": 40.3521173, "lon": -3.6943673}, {"type": "node", "id": 316434230, "lat": 40.3522721, "lon": -3.6943746}, {"type": "node", "id": 316437242, "lat": 40.3512099, "lon": -3.6941958}, {"type": "node", "id": 316437991, "lat": 40.3514214, "lon": -3.6935119}, {"type": "node", "id": 316438068, "lat": 40.3513427, "lon": -3.6936074}, {"type": "node", "id": 316438069, "lat": 40.3512682, "lon": -3.6936048, "tags": {"highway": "give_way"}}, {"type": "node", "id": 316438070, "lat": 40.3511568, "lon": -3.6935735}, {"type": "node", "id": 316438306, "lat": 40.3511014, "lon": -3.69299}, {"type": "node", "id": 318140097, "lat": 40.3525442, "lon": -3.6934454}, {"type": "node", "id": 338979656, "lat": 40.3510769, "lon": -3.6946107, "tags": {"bus": "yes", "public_transport": "stop_position"}}, {"type": "node", "id": 401883746, "lat": 40.3609461, "lon": -3.6937413, "tags": {"crossing": "traffic_signals", "highway": "crossing"}}, {"type": "node", "id": 401883747, "lat": 40.3591923, "lon": -3.6935041}, {"type": "node", "id": 401883748, "lat": 40.3568459, "lon": -3.6933432, "tags": {"crossing": "traffic_signals", "crossing:markings": "dots", "highway": "traffic_signals"}}, {"type": "node", "id": 401883749, "lat": 40.3562781, "lon": -3.6933313, "tags": {"crossing": "traffic_signals", "crossing:markings": "dots", "highway": "traffic_signals"}}, {"type": "node", "id": 401883750, "lat": 40.3530114, "lon": -3.6932376, "tags": {"bicycle": "yes", "crossing": "uncontrolled", "highway": "crossing"}}, {"type": "node", "id": 401883751, "lat": 40.3524305, "lon": -3.6932176, "tags": {"bicycle": "yes", "crossing": "traffic_signals", "crossing:markings": "dots", "highway": "traffic_signals"}}, {"type": "node", "id": 401883752, "lat": 40.3517782, "lon": -3.693174}, {"type": "node", "id": 446263186, "lat": 40.3507742, "lon": -3.6955877, "tags": {"highway": "traffic_signals"}}, {"type": "node", "id": 1437771417, "lat": 40.3519228, "lon": -3.6930564}, {"type": "node", "id": 1439699468, "lat": 40.3511006, "lon": -3.6943318, "tags": {"bench": "yes", "bus": "yes", "highway": "bus_stop", "name": "Alcocer-Escoriaza", "operator": "EMT Madrid", "public_transport": "platform", "ref": "1789", "shelter": "yes", "source": "https://navegapormadrid.emtmadrid.es/app/"}}, {"type": "node", "id": 1439699471, "lat": 40.351141, "lon": -3.6946416, "tags": {"bench": "yes", "bus": "yes", "highway": "bus_stop", "name": "Alcocer-Villaverde Cruce", "operator": "EMT Madrid", "public_transport": "platform", "ref": "1790", "shelter": "yes", "source": "https://navegapormadrid.emtmadrid.es/app/"}}, {"type": "node", "id": 1709862032, "lat": 40.3510278, "lon": -3.6936041}, {"type": "node", "id": 1709862037, "lat": 40.3508568, "lon": -3.6936042, "tags": {"crossing": "uncontrolled", "highway": "crossing"}}, {"type": "node", "id": 1709862040, "lat": 40.3509155, "lon": -3.6936699}, {"type": "node", "id": 1709862045, "lat": 40.3504351, "lon": -3.6966454}, {"type": "node", "id": 1709862053, "lat": 40.3511893, "lon": -3.6942589, "tags": {"highway": "crossing"}}, {"type": "node", "id": 1709862078, "lat": 40.3498681, "lon": -3.6941804}, {"type": "node", "id": 1709862099, "lat": 40.3510207, "lon": -3.6937347}, {"type": "node", "id": 1709862110, "lat": 40.3506376, "lon": -3.6941737}, {"type": "node", "id": 1735114338, "lat": 40.3560755, "lon": -3.6933233}, {"type": "node", "id": 1735114346, "lat": 40.3571342, "lon": -3.6933692, "tags": {"highway": "traffic_signals"}}, {"type": "node", "id": 1735114354, "lat": 40.3586249, "lon": -3.693458, "tags": {"highway": "traffic_signals"}}, {"type": "node", "id": 1735114357, "lat": 40.3586968, "lon": -3.6934624, "tags": {"highway": "traffic_signals"}}, {"type": "node", "id": 1735114365, "lat": 40.3608012, "lon": -3.693693, "tags": {"highway": "traffic_signals"}}, {"type": "node", "id": 1736603500, "lat": 40.3600662, "lon": -3.6935878}, {"type": "node", "id": 1740617532, "lat": 40.3529525, "lon": -3.6932198}, {"type": "node", "id": 1740617998, "lat": 40.3561359, "lon": -3.693324, "tags": {"highway": "traffic_signals"}}, {"type": "node", "id": 1740618003, "lat": 40.356231, "lon": -3.6933251, "tags": {"highway": "traffic_signals"}}, {"type": "node", "id": 2043484922, "lat": 40.3509518, "lon": -3.6931631, "tags": {"crossing": "traffic_signals", "crossing:markings": "dots", "highway": "crossing"}}, {"type": "node", "id": 3136517458, "lat": 40.3521017, "lon": -3.693123, "tags": {"crossing": "no", "highway": "traffic_signals"}}, {"type": "node", "id": 3136517555, "lat": 40.3513206, "lon": -3.6931465}, {"type": "node", "id": 3136517564, "lat": 40.3522374, "lon": -3.6931216, "tags": {"crossing": "traffic_signals", "crossing:markings": "dots", "highway": "traffic_signals"}}, {"type": "node", "id": 3136755795, "lat": 40.3591445, "lon": -3.6935016, "tags": {"highway": "crossing"}}, {"type": "node", "id": 3323361463, "lat": 40.3608732, "lon": -3.6937305, "tags": {"highway": "traffic_signals"}}, {"type": "node", "id": 3326943569, "lat": 40.3510797, "lon": -3.6933852}, {"type": "node", "id": 3328399481, "lat": 40.3579854, "lon": -3.693403}, {"type": "node", "id": 3328399738, "lat": 40.3602873, "lon": -3.6936141, "tags": {"highway": "crossing"}}, {"type": "node", "id": 3328399739, "lat": 40.360434, "lon": -3.6936316}, {"type": "node", "id": 3328399740, "lat": 40.3606404, "lon": -3.693657}, {"type": "node", "id": 3336274707, "lat": 40.3511226, "lon": -3.6932448}, {"type": "node", "id": 3336274708, "lat": 40.3511308, "lon": -3.6933815}, {"type": "node", "id": 3336274709, "lat": 40.3511503, "lon": -3.6934371}, {"type": "node", "id": 3336274710, "lat": 40.3512442, "lon": -3.6935277}, {"type": "node", "id": 3336274711, "lat": 40.3512805, "lon": -3.6935315}, {"type": "node", "id": 3336274712, "lat": 40.35136, "lon": -3.6935088}, {"type": "node", "id": 3336274713, "lat": 40.3513911, "lon": -3.6934748}, {"type": "node", "id": 3336274714, "lat": 40.3515054, "lon": -3.6933132}, {"type": "node", "id": 3336274715, "lat": 40.35156, "lon": -3.6932344}, {"type": "node", "id": 3336274725, "lat": 40.3521094, "lon": -3.6934576}, {"type": "node", "id": 3336274726, "lat": 40.3521823, "lon": -3.6934035}, {"type": "node", "id": 3494953462, "lat": 40.3497829, "lon": -3.6941802}, {"type": "node", "id": 3494953467, "lat": 40.3499626, "lon": -3.6941786}, {"type": "node", "id": 3494953481, "lat": 40.3506945, "lon": -3.6958463, "tags": {"crossing": "uncontrolled", "highway": "crossing"}}, {"type": "node", "id": 3494953482, "lat": 40.3507327, "lon": -3.6941733}, {"type": "node", "id": 3494953485, "lat": 40.3507994, "lon": -3.6937117}, {"type": "node", "id": 3494953488, "lat": 40.3513387, "lon": -3.6937808, "tags": {"highway": "crossing"}}, {"type": "node", "id": 3496820499, "lat": 40.3507367, "lon": -3.6954489}, {"type": "node", "id": 3496820518, "lat": 40.351049, "lon": -3.6944281}, {"type": "node", "id": 3496820526, "lat": 40.3511097, "lon": -3.6948895}, {"type": "node", "id": 3496820527, "lat": 40.3511156, "lon": -3.6947334}, {"type": "node", "id": 3496820529, "lat": 40.3511151, "lon": -3.6942324}, {"type": "node", "id": 3496820532, "lat": 40.3511469, "lon": -3.6938113}, {"type": "node", "id": 3496820534, "lat": 40.3511584, "lon": -3.6947219}, {"type": "node", "id": 3496820540, "lat": 40.3512581, "lon": -3.6944178}, {"type": "node", "id": 3496820541, "lat": 40.3512598, "lon": -3.6942803}, {"type": "node", "id": 3496820542, "lat": 40.3512993, "lon": -3.6937682}, {"type": "node", "id": 3496820544, "lat": 40.3513576, "lon": -3.6938584}, {"type": "node", "id": 3496820546, "lat": 40.3513783, "lon": -3.6939467}, {"type": "node", "id": 3496820547, "lat": 40.3513784, "lon": -3.6937987, "tags": {"highway": "crossing"}}, {"type": "node", "id": 3496820550, "lat": 40.3514533, "lon": -3.6935801}, {"type": "node", "id": 3496820563, "lat": 40.3516181, "lon": -3.6936171}, {"type": "node", "id": 3496820828, "lat": 40.3526537, "lon": -3.6943937}, {"type": "node", "id": 3496820830, "lat": 40.3526666, "lon": -3.6939018, "tags": {"highway": "crossing"}}, {"type": "node", "id": 3496820831, "lat": 40.3526726, "lon": -3.6936467}, {"type": "node", "id": 3510203754, "lat": 40.3543468, "lon": -3.6932658, "tags": {"highway": "traffic_signals"}}, {"type": "node", "id": 3510203948, "lat": 40.3554208, "lon": -3.6933015, "tags": {"highway": "crossing"}}, {"type": "node", "id": 3512394990, "lat": 40.3499012, "lon": -3.6941791}, {"type": "node", "id": 3512395023, "lat": 40.3506843, "lon": -3.6954632}, {"type": "node", "id": 3512395027, "lat": 40.3511326, "lon": -3.6941719}, {"type": "node", "id": 3544594115, "lat": 40.349781, "lon": -3.6931704, "tags": {"crossing": "no", "highway": "traffic_signals"}}, {"type": "node", "id": 3544594124, "lat": 40.3498974, "lon": -3.6935656, "tags": {"crossing": "uncontrolled", "crossing:markings": "yes", "crossing:signals": "no", "highway": "crossing"}}, {"type": "node", "id": 3544594148, "lat": 40.3500772, "lon": -3.6941758}, {"type": "node", "id": 3544594154, "lat": 40.350127, "lon": -3.6941779}, {"type": "node", "id": 3544594164, "lat": 40.3503569, "lon": -3.6941748}, {"type": "node", "id": 3544594581, "lat": 40.3509114, "lon": -3.6941675}, {"type": "node", "id": 3544594595, "lat": 40.3509294, "lon": -3.6945702}, {"type": "node", "id": 3544594601, "lat": 40.3509397, "lon": -3.693954}, {"type": "node", "id": 3544594606, "lat": 40.3509537, "lon": -3.6932507}, {"type": "node", "id": 3544594611, "lat": 40.3509986, "lon": -3.6945953}, {"type": "node", "id": 3544594612, "lat": 40.3510228, "lon": -3.6938996}, {"type": "node", "id": 3544594614, "lat": 40.3510637, "lon": -3.6932628, "tags": {"crossing": "no", "highway": "traffic_signals"}}, {"type": "node", "id": 3544594618, "lat": 40.3511109, "lon": -3.6934862}, {"type": "node", "id": 3547342530, "lat": 40.3507329, "lon": -3.6932894}, {"type": "node", "id": 3547342536, "lat": 40.3508447, "lon": -3.693468}, {"type": "node", "id": 3547342542, "lat": 40.3508456, "lon": -3.6937268}, {"type": "node", "id": 3547342547, "lat": 40.3508913, "lon": -3.6935014}, {"type": "node", "id": 3547342548, "lat": 40.3508861, "lon": -3.6932503}, {"type": "node", "id": 3547342559, "lat": 40.350982, "lon": -3.6932514}, {"type": "node", "id": 3547342573, "lat": 40.3510902, "lon": -3.694283}, {"type": "node", "id": 3550750764, "lat": 40.3508713, "lon": -3.6935015}, {"type": "node", "id": 3631474502, "lat": 40.351078, "lon": -3.694833}, {"type": "node", "id": 3631474504, "lat": 40.3510886, "lon": -3.6948654}, {"type": "node", "id": 3631474505, "lat": 40.3511113, "lon": -3.6947092}, {"type": "node", "id": 3631474509, "lat": 40.3511291, "lon": -3.6946903}, {"type": "node", "id": 3631474510, "lat": 40.3511469, "lon": -3.6948983}, {"type": "node", "id": 3631474514, "lat": 40.3512025, "lon": -3.694595}, {"type": "node", "id": 3631474515, "lat": 40.3512272, "lon": -3.6945161}, {"type": "node", "id": 3631474516, "lat": 40.3512238, "lon": -3.694397}, {"type": "node", "id": 3631474523, "lat": 40.3512645, "lon": -3.6943973}, {"type": "node", "id": 3631474535, "lat": 40.3513606, "lon": -3.6949463}, {"type": "node", "id": 3631474536, "lat": 40.3513617, "lon": -3.6949071}, {"type": "node", "id": 3631474537, "lat": 40.3513702, "lon": -3.6946023}, {"type": "node", "id": 3631474553, "lat": 40.3514244, "lon": -3.6944029}, {"type": "node", "id": 3631474558, "lat": 40.3514381, "lon": -3.6942938}, {"type": "node", "id": 3631474560, "lat": 40.3514438, "lon": -3.6939313}, {"type": "node", "id": 3631478636, "lat": 40.3516588, "lon": -3.6947493}, {"type": "node", "id": 3631478639, "lat": 40.3516608, "lon": -3.6946061}, {"type": "node", "id": 3631478640, "lat": 40.3516618, "lon": -3.6945266}, {"type": "node", "id": 3631478677, "lat": 40.3517863, "lon": -3.6944179}, {"type": "node", "id": 3631478806, "lat": 40.351882, "lon": -3.6949633}, {"type": "node", "id": 3631478808, "lat": 40.3518832, "lon": -3.6949262}, {"type": "node", "id": 3631478810, "lat": 40.3518921, "lon": -3.6946156}, {"type": "node", "id": 3631478841, "lat": 40.3520108, "lon": -3.6944254}, {"type": "node", "id": 3631478855, "lat": 40.3520224, "lon": -3.6947194}, {"type": "node", "id": 3631478856, "lat": 40.3520245, "lon": -3.6946227}, {"type": "node", "id": 3631478857, "lat": 40.3520271, "lon": -3.6945381}, {"type": "node", "id": 3631478869, "lat": 40.3520942, "lon": -3.6945407}, {"type": "node", "id": 3631478871, "lat": 40.3520956, "lon": -3.694484}, {"type": "node", "id": 3631478872, "lat": 40.352097, "lon": -3.6944314}, {"type": "node", "id": 3631478884, "lat": 40.3521224, "lon": -3.694681}, {"type": "node", "id": 3631478885, "lat": 40.3521246, "lon": -3.6945924}, {"type": "node", "id": 3631478888, "lat": 40.3521269, "lon": -3.6944984}, {"type": "node", "id": 3631478891, "lat": 40.352131, "lon": -3.6949713}, {"type": "node", "id": 3631479094, "lat": 40.3521321, "lon": -3.6949355}, {"type": "node", "id": 3631479095, "lat": 40.3521371, "lon": -3.6947512}, {"type": "node", "id": 3631479096, "lat": 40.3521391, "lon": -3.6946816}, {"type": "node", "id": 3631479102, "lat": 40.3521617, "lon": -3.694547}, {"type": "node", "id": 3631479104, "lat": 40.3521627, "lon": -3.6944865}, {"type": "node", "id": 3631479136, "lat": 40.3522688, "lon": -3.6946007}, {"type": "node", "id": 3631479137, "lat": 40.3522696, "lon": -3.6945512}, {"type": "node", "id": 3631479176, "lat": 40.3524143, "lon": -3.6946908}, {"type": "node", "id": 3631479302, "lat": 40.3525247, "lon": -3.6946943}, {"type": "node", "id": 3631479306, "lat": 40.3525303, "lon": -3.6946135}, {"type": "node", "id": 3631479310, "lat": 40.3525499, "lon": -3.6946455}, {"type": "node", "id": 3631479322, "lat": 40.3526492, "lon": -3.694566}, {"type": "node", "id": 3634109177, "lat": 40.3498908, "lon": -3.6936115, "tags": {"highway": "crossing"}}, {"type": "node", "id": 3634109178, "lat": 40.3502076, "lon": -3.6936238}, {"type": "node", "id": 3634109179, "lat": 40.3504234, "lon": -3.6936268}, {"type": "node", "id": 3634109181, "lat": 40.3507774, "lon": -3.6936378}, {"type": "node", "id": 3634109182, "lat": 40.3508556, "lon": -3.6936481, "tags": {"crossing": "uncontrolled", "highway": "crossing"}}, {"type": "node", "id": 3634109183, "lat": 40.3509719, "lon": -3.6936956}, {"type": "node", "id": 3634110497, "lat": 40.3513666, "lon": -3.6947322}, {"type": "node", "id": 3634110500, "lat": 40.3514095, "lon": -3.6939337}, {"type": "node", "id": 3634110501, "lat": 40.3514316, "lon": -3.6936433}, {"type": "node", "id": 3634110502, "lat": 40.3514448, "lon": -3.6937313}, {"type": "node", "id": 3634110505, "lat": 40.3514751, "lon": -3.6936533}, {"type": "node", "id": 3634110506, "lat": 40.3514825, "lon": -3.6945479}, {"type": "node", "id": 3634110507, "lat": 40.3514828, "lon": -3.694522}, {"type": "node", "id": 3634110508, "lat": 40.3514977, "lon": -3.6936256}, {"type": "node", "id": 3634110509, "lat": 40.3514842, "lon": -3.6934826}, {"type": "node", "id": 3634110518, "lat": 40.351503, "lon": -3.6947387}, {"type": "node", "id": 3634110519, "lat": 40.3515042, "lon": -3.6946938}, {"type": "node", "id": 3634110521, "lat": 40.3515065, "lon": -3.6946072}, {"type": "node", "id": 3634110522, "lat": 40.351508, "lon": -3.6945485}, {"type": "node", "id": 3634110523, "lat": 40.3515087, "lon": -3.6945226}, {"type": "node", "id": 3634110525, "lat": 40.3515134, "lon": -3.6934296}, {"type": "node", "id": 3634110530, "lat": 40.3515789, "lon": -3.6933727}, {"type": "node", "id": 3634110533, "lat": 40.3515931, "lon": -3.6946973}, {"type": "node", "id": 3634110534, "lat": 40.351631, "lon": -3.6945257}, {"type": "node", "id": 3634110535, "lat": 40.3516341, "lon": -3.6944138}, {"type": "node", "id": 3634110540, "lat": 40.3516586, "lon": -3.6933225}, {"type": "node", "id": 3634110541, "lat": 40.3516595, "lon": -3.6946994}, {"type": "node", "id": 3634110543, "lat": 40.3517491, "lon": -3.6932896}, {"type": "node", "id": 3634110546, "lat": 40.3517825, "lon": -3.6946111}, {"type": "node", "id": 3634110547, "lat": 40.3517841, "lon": -3.6945305}, {"type": "node", "id": 3634110551, "lat": 40.351867, "lon": -3.6932649}, {"type": "node", "id": 3634110552, "lat": 40.3518881, "lon": -3.6947569}, {"type": "node", "id": 3634110560, "lat": 40.3520014, "lon": -3.6932341}, {"type": "node", "id": 3634110567, "lat": 40.352104, "lon": -3.6932202}, {"type": "node", "id": 3634110577, "lat": 40.3522336, "lon": -3.6932241, "tags": {"highway": "traffic_signals"}}, {"type": "node", "id": 3637128627, "lat": 40.351415, "lon": -3.6939024}, {"type": "node", "id": 3637128628, "lat": 40.3514304, "lon": -3.6938615}, {"type": "node", "id": 3637128630, "lat": 40.3514546, "lon": -3.6938377}, {"type": "node", "id": 3637128635, "lat": 40.3514919, "lon": -3.6938258}, {"type": "node", "id": 3637128636, "lat": 40.3514871, "lon": -3.6935219}, {"type": "node", "id": 3637128643, "lat": 40.351516, "lon": -3.6934837}, {"type": "node", "id": 3637128644, "lat": 40.3515166, "lon": -3.6943226}, {"type": "node", "id": 3637128646, "lat": 40.3515232, "lon": -3.6939217}, {"type": "node", "id": 3637128651, "lat": 40.3515331, "lon": -3.6936151}, {"type": "node", "id": 3637128658, "lat": 40.3515422, "lon": -3.6934533}, {"type": "node", "id": 3637128664, "lat": 40.3515795, "lon": -3.6934182}, {"type": "node", "id": 3637128670, "lat": 40.3516008, "lon": -3.6943255}, {"type": "node", "id": 3637128678, "lat": 40.3516094, "lon": -3.6939248}, {"type": "node", "id": 3637128680, "lat": 40.3516146, "lon": -3.6938296}, {"type": "node", "id": 3637128683, "lat": 40.351618, "lon": -3.6936243}, {"type": "node", "id": 3637128685, "lat": 40.3516188, "lon": -3.6935448}, {"type": "node", "id": 3637128894, "lat": 40.3516289, "lon": -3.6933878}, {"type": "node", "id": 3637128900, "lat": 40.351645, "lon": -3.6934583}, {"type": "node", "id": 3637128902, "lat": 40.3516466, "lon": -3.6934133}, {"type": "node", "id": 3637128904, "lat": 40.3516486, "lon": -3.6935046}, {"type": "node", "id": 3637128905, "lat": 40.351649, "lon": -3.6938307}, {"type": "node", "id": 3637128907, "lat": 40.3516533, "lon": -3.693625}, {"type": "node", "id": 3637128913, "lat": 40.3516758, "lon": -3.6933683}, {"type": "node", "id": 3637128914, "lat": 40.3516763, "lon": -3.6935483}, {"type": "node", "id": 3637128924, "lat": 40.351704, "lon": -3.6935503}, {"type": "node", "id": 3637128928, "lat": 40.3517116, "lon": -3.6933591}, {"type": "node", "id": 3637128944, "lat": 40.3517672, "lon": -3.6943312}, {"type": "node", "id": 3637128947, "lat": 40.3517763, "lon": -3.6939309}, {"type": "node", "id": 3637128948, "lat": 40.3517771, "lon": -3.6933624}, {"type": "node", "id": 3637128958, "lat": 40.3518412, "lon": -3.6935536}, {"type": "node", "id": 3637128960, "lat": 40.3518514, "lon": -3.6943341}, {"type": "node", "id": 3637128961, "lat": 40.3518589, "lon": -3.6939339}, {"type": "node", "id": 3637128969, "lat": 40.3518893, "lon": -3.6947155}, {"type": "node", "id": 3637128970, "lat": 40.3519113, "lon": -3.6938385}, {"type": "node", "id": 3637128971, "lat": 40.3519158, "lon": -3.6936297}, {"type": "node", "id": 3637128982, "lat": 40.3519789, "lon": -3.6939383}, {"type": "node", "id": 3637128993, "lat": 40.3520389, "lon": -3.6943405}, {"type": "node", "id": 3637128995, "lat": 40.352044, "lon": -3.6939403}, {"type": "node", "id": 3637129000, "lat": 40.3520767, "lon": -3.694679}, {"type": "node", "id": 3637129001, "lat": 40.3520789, "lon": -3.6945904}, {"type": "node", "id": 3637129002, "lat": 40.3520852, "lon": -3.6933677}, {"type": "node", "id": 3637129005, "lat": 40.3521206, "lon": -3.6943432}, {"type": "node", "id": 3637129010, "lat": 40.3521277, "lon": -3.693943}, {"type": "node", "id": 3637129011, "lat": 40.3521327, "lon": -3.693847}, {"type": "node", "id": 3637129013, "lat": 40.3521356, "lon": -3.6936327}, {"type": "node", "id": 3637129014, "lat": 40.3521401, "lon": -3.6933432}, {"type": "node", "id": 3637129024, "lat": 40.3521724, "lon": -3.6938487}, {"type": "node", "id": 3637129025, "lat": 40.3521755, "lon": -3.693633}, {"type": "node", "id": 3637129026, "lat": 40.3521775, "lon": -3.6935608}, {"type": "node", "id": 3637129027, "lat": 40.3521805, "lon": -3.6934616}, {"type": "node", "id": 3637129049, "lat": 40.3522855, "lon": -3.6943487}, {"type": "node", "id": 3637129050, "lat": 40.3522941, "lon": -3.6939483}, {"type": "node", "id": 3637129056, "lat": 40.3523732, "lon": -3.6932199, "tags": {"highway": "traffic_signals"}}, {"type": "node", "id": 3637129058, "lat": 40.3523722, "lon": -3.6943516}, {"type": "node", "id": 3637129059, "lat": 40.3523777, "lon": -3.6939509}, {"type": "node", "id": 3637129069, "lat": 40.3524139, "lon": -3.6938563}, {"type": "node", "id": 3637129070, "lat": 40.3524149, "lon": -3.6933498}, {"type": "node", "id": 3637129071, "lat": 40.352416, "lon": -3.6936428}, {"type": "node", "id": 3637129072, "lat": 40.3524168, "lon": -3.693565}, {"type": "node", "id": 3637129073, "lat": 40.3524179, "lon": -3.6933286}, {"type": "node", "id": 3637129074, "lat": 40.3524189, "lon": -3.6934689}, {"type": "node", "id": 3637129077, "lat": 40.3524366, "lon": -3.6934136}, {"type": "node", "id": 3637129083, "lat": 40.3524527, "lon": -3.6938587}, {"type": "node", "id": 3637129086, "lat": 40.3524578, "lon": -3.6935675}, {"type": "node", "id": 3637129210, "lat": 40.3525628, "lon": -3.694358}, {"type": "node", "id": 3637129213, "lat": 40.3525723, "lon": -3.6939571}, {"type": "node", "id": 3637129222, "lat": 40.3526545, "lon": -3.694361}, {"type": "node", "id": 3637129223, "lat": 40.3526651, "lon": -3.69396}, {"type": "node", "id": 3637129224, "lat": 40.3526673, "lon": -3.6938643}, {"type": "node", "id": 3637129225, "lat": 40.3526735, "lon": -3.6935807}, {"type": "node", "id": 3890265749, "lat": 40.3483548, "lon": -3.6935052, "tags": {"highway": "crossing"}}, {"type": "node", "id": 3890265754, "lat": 40.3484268, "lon": -3.6935047}, {"type": "node", "id": 3890266066, "lat": 40.3485039, "lon": -3.6935371}, {"type": "node", "id": 3890266100, "lat": 40.348732, "lon": -3.693578}, {"type": "node", "id": 3890266109, "lat": 40.3489284, "lon": -3.6935889}, {"type": "node", "id": 3890266110, "lat": 40.3497286, "lon": -3.6936073, "tags": {"highway": "crossing"}}, {"type": "node", "id": 5219770557, "lat": 40.3568994, "lon": -3.6933594, "tags": {"highway": "traffic_signals"}}, {"type": "node", "id": 5219770560, "lat": 40.3579725, "lon": -3.6934022, "tags": {"highway": "crossing"}}, {"type": "node", "id": 6179458817, "lat": 40.351215, "lon": -3.6940592}, {"type": "node", "id": 6179458818, "lat": 40.351224, "lon": -3.6938845}, {"type": "node", "id": 6179458819, "lat": 40.3512655, "lon": -3.6940562}, {"type": "node", "id": 6179458820, "lat": 40.3515635, "lon": -3.6932438}, {"type": "node", "id": 6179458821, "lat": 40.3515631, "lon": -3.6932384}, {"type": "node", "id": 6179458822, "lat": 40.3515609, "lon": -3.6932492}, {"type": "node", "id": 6179458823, "lat": 40.3513239, "lon": -3.693525}, {"type": "node", "id": 6179458824, "lat": 40.3512186, "lon": -3.693518}, {"type": "node", "id": 6179458825, "lat": 40.3511953, "lon": -3.6934995}, {"type": "node", "id": 6179458826, "lat": 40.3511709, "lon": -3.6934734}, {"type": "node", "id": 6179458828, "lat": 40.3510629, "lon": -3.6937747}, {"type": "node", "id": 6179458829, "lat": 40.3511999, "lon": -3.69373, "tags": {"crossing": "marked", "crossing:markings": "yes", "highway": "crossing"}}, {"type": "node", "id": 6179458830, "lat": 40.3512447, "lon": -3.6937188}, {"type": "node", "id": 6179458831, "lat": 40.3513262, "lon": -3.6937217}, {"type": "node", "id": 6179458832, "lat": 40.3513524, "lon": -3.6937318, "tags": {"crossing": "marked", "crossing:markings": "yes", "highway": "crossing"}}, {"type": "node", "id": 6179458833, "lat": 40.3513971, "lon": -3.6937436, "tags": {"highway": "crossing"}}, {"type": "node", "id": 6649990969, "lat": 40.3510805, "lon": -3.6941661}, {"type": "node", "id": 6650007819, "lat": 40.3510727, "lon": -3.6940656}, {"type": "node", "id": 6650007820, "lat": 40.3510639, "lon": -3.6940134}, {"type": "node", "id": 6650007821, "lat": 40.3510501, "lon": -3.6939632}, {"type": "node", "id": 6650007822, "lat": 40.3510316, "lon": -3.6939158}, {"type": "node", "id": 6650007823, "lat": 40.3510065, "lon": -3.6938687}, {"type": "node", "id": 6650007824, "lat": 40.3509768, "lon": -3.6938267}, {"type": "node", "id": 6650007825, "lat": 40.350943, "lon": -3.6937905}, {"type": "node", "id": 6650007826, "lat": 40.3509057, "lon": -3.6937608}, {"type": "node", "id": 6650007827, "lat": 40.3508656, "lon": -3.6937381}, {"type": "node", "id": 6650007828, "lat": 40.3508232, "lon": -3.6937188}, {"type": "node", "id": 6650007829, "lat": 40.3510766, "lon": -3.6941234}, {"type": "node", "id": 6652847231, "lat": 40.3508912, "lon": -3.6936933}, {"type": "node", "id": 6652847232, "lat": 40.3509788, "lon": -3.6937388}, {"type": "node", "id": 6652847233, "lat": 40.3510534, "lon": -3.6938042}, {"type": "node", "id": 6652847234, "lat": 40.3510918, "lon": -3.6938505}, {"type": "node", "id": 6652847235, "lat": 40.3511145, "lon": -3.693908}, {"type": "node", "id": 6652847236, "lat": 40.3511388, "lon": -3.6940118}, {"type": "node", "id": 6652847237, "lat": 40.3511433, "lon": -3.6941073}, {"type": "node", "id": 6652847248, "lat": 40.3511379, "lon": -3.6942426}, {"type": "node", "id": 6652847265, "lat": 40.3511676, "lon": -3.6937997}, {"type": "node", "id": 6652847266, "lat": 40.3511515, "lon": -3.6937419}, {"type": "node", "id": 6652847270, "lat": 40.3511379, "lon": -3.6937452}, {"type": "node", "id": 6654945678, "lat": 40.3498292, "lon": -3.6941792}, {"type": "node", "id": 6654975663, "lat": 40.3508541, "lon": -3.693678}, {"type": "node", "id": 6654975680, "lat": 40.3505162, "lon": -3.6934665}, {"type": "node", "id": 6654975682, "lat": 40.3508433, "lon": -3.6935015}, {"type": "node", "id": 6657552394, "lat": 40.3508823, "lon": -3.6949743}, {"type": "node", "id": 6660553423, "lat": 40.3504973, "lon": -3.6934669}, {"type": "node", "id": 6660573587, "lat": 40.3504985, "lon": -3.6933128}, {"type": "node", "id": 6660573594, "lat": 40.3504975, "lon": -3.6934293}, {"type": "node", "id": 6660573595, "lat": 40.3504988, "lon": -3.6932887}, {"type": "node", "id": 8327088600, "lat": 40.3500582, "lon": -3.6931766, "tags": {"bus": "yes", "public_transport": "stop_position"}}, {"type": "node", "id": 8346433170, "lat": 40.3511592, "lon": -3.6943594, "tags": {"bus": "yes", "public_transport": "stop_position"}}, {"type": "node", "id": 8467354190, "lat": 40.3504577, "lon": -3.6931792, "tags": {"bus": "yes", "public_transport": "stop_position"}}, {"type": "node", "id": 9385908072, "lat": 40.356325, "lon": -3.6933323}, {"type": "node", "id": 9385908073, "lat": 40.3567975, "lon": -3.6933422}, {"type": "node", "id": 9741530813, "lat": 40.3512582, "lon": -3.6931492, "tags": {"crossing": "no", "highway": "traffic_signals"}}, {"type": "node", "id": 9741579891, "lat": 40.351661, "lon": -3.6932283}, {"type": "node", "id": 10699707658, "lat": 40.3519106, "lon": -3.6938713}, {"type": "node", "id": 11749212794, "lat": 40.3613965, "lon": -3.6937995}, {"type": "node", "id": 11749212810, "lat": 40.354372, "lon": -3.6932666, "tags": {"highway": "traffic_signals"}}, {"type": "node", "id": 11772636998, "lat": 40.3521987, "lon": -3.6938495}, {"type": "node", "id": 11772636999, "lat": 40.3522013, "lon": -3.6938632}, {"type": "node", "id": 11772637000, "lat": 40.3522034, "lon": -3.6938831, "tags": {"highway": "crossing"}}, {"type": "node", "id": 11772637001, "lat": 40.3522073, "lon": -3.6939455}, {"type": "node", "id": 11772637023, "lat": 40.3506805, "lon": -3.6955033}, {"type": "node", "id": 11795819596, "lat": 40.3523801, "lon": -3.6931913}, {"type": "node", "id": 11795819597, "lat": 40.3516504, "lon": -3.6933213}, {"type": "node", "id": 11795819598, "lat": 40.3517536, "lon": -3.6932704}, {"type": "node", "id": 11795819599, "lat": 40.3518569, "lon": -3.6932382}, {"type": "node", "id": 11795819600, "lat": 40.3520398, "lon": -3.6932047}, {"type": "node", "id": 11795819601, "lat": 40.3522346, "lon": -3.6931981}, {"type": "node", "id": 11795819602, "lat": 40.3523198, "lon": -3.6931939}, {"type": "node", "id": 12218920865, "lat": 40.3516527, "lon": -3.6933262, "tags": {"highway": "crossing"}}, {"type": "node", "id": 12296054710, "lat": 40.3528452, "lon": -3.6932193}, {"type": "node", "id": 12296054719, "lat": 40.3525151, "lon": -3.693218}, {"type": "way", "id": 23056664, "nodes": [316437991, 6179458832, 3494953488, 6179458819, 316437242], "tags": {"highway": "secondary", "maxspeed": "50", "name": "Calle de Alcocer", "oneway": "yes", "postal_code": "28041"}}, {"type": "way", "id": 28777833, "nodes": [316433492, 3496820830, 11772637000, 10699707658, 316433575], "tags": {"highway": "residential", "name": "Calle de Lezo", "oneway": "yes", "postal_code": "28041"}}, {"type": "way", "id": 28777838, "nodes": [316433575, 3631474560, 3631474558, 316433576], "tags": {"highway": "residential", "name": "Calle de Alcocer", "oneway": "yes", "postal_code": "28041"}}, {"type": "way", "id": 28777839, "nodes": [316433576, 316434210, 316434230, 3496820828, 316433577], "tags": {"highway": "residential", "name": "Calle de Lazcano", "oneway": "yes", "postal_code": "28041"}}, {"type": "way", "id": 28778287, "nodes": [316437242, 1709862053, 8346433170, 338979656, 316433654, 446263186, 306257967, 3494953481, 306258499, 1709862045, 248795116], "tags": {"highway": "secondary", "lanes": "2", "lanes:backward": "1", "lanes:forward": "1", "maxspeed": "50", "name": "Calle de Alcocer", "oneway": "no", "postal_code": "28041", "sidewalk": "both"}}, {"type": "way", "id": 28778288, "nodes": [316437242, 6179458817, 6179458818, 248795318, 6179458829, 316438070], "tags": {"highway": "secondary", "maxspeed": "50", "name": "Calle de Alcocer", "oneway": "yes", "postal_code": "28021"}}, {"type": "way", "id": 28778527, "nodes": [316437991, 316438068, 316438069, 316438070], "tags": {"highway": "secondary", "lanes": "4", "maxspeed": "50", "oneway": "yes", "postal_code": "28021", "turn:lanes": "left|left|through|through"}}, {"type": "way", "id": 28938669, "nodes": [318140097, 3637129077, 3336274726, 3336274725, 248790764], "tags": {"highway": "residential", "name": "Paseo de Gigantes y Cabezudos", "postal_code": "28041"}}, {"type": "way", "id": 34563630, "nodes": [248790605, 3136517564, 3136517458, 26282204, 248795163], "tags": {"highway": "primary", "lanes": "3", "maxspeed": "50", "name": "Avenida de Andaluc\u00eda", "oneway": "yes", "postal_code": "28041", "wikidata": "Q5714182", "wikipedia": "es:Avenida de Andaluc\u00eda (Madrid)"}}, {"type": "way", "id": 34563631, "nodes": [248795319, 2043484922, 26282212, 8467354190, 8327088600, 3544594115, 306258325], "tags": {"highway": "primary", "lanes": "4", "maxspeed": "50", "name": "Avenida de Andaluc\u00eda", "oneway": "yes", "postal_code": "28021", "wikidata": "Q5714182", "wikipedia": "es:Avenida de Andaluc\u00eda (Madrid)"}}, {"type": "way", "id": 34609312, "nodes": [11749212794, 401883746, 3323361463, 1735114365, 3328399740, 3328399739, 3328399738, 1736603500, 401883747, 3136755795, 1735114357, 1735114354, 3328399481, 5219770560, 1735114346, 5219770557, 401883748, 9385908073, 9385908072, 401883749, 1740618003, 1740617998, 1735114338, 3510203948, 11749212810, 3510203754, 401883750, 1740617532, 12296054710, 12296054719, 401883751, 3637129056, 3634110577, 3634110567], "tags": {"highway": "cycleway", "lit": "yes", "name": "Avenida de Andaluc\u00eda", "segregated": "yes"}}, {"type": "way", "id": 41849236, "nodes": [248795163, 3136517555, 9741530813, 248795319], "tags": {"highway": "primary", "lanes": "4", "maxspeed": "50", "name": "Avenida de Andaluc\u00eda", "oneway": "yes", "postal_code": "28021", "wikidata": "Q5714182", "wikipedia": "es:Avenida de Andaluc\u00eda (Madrid)"}}, {"type": "way", "id": 41849238, "nodes": [248795163, 401883752, 9741579891, 248795115, 316437991], "tags": {"highway": "secondary", "maxspeed": "50", "name": "Calle de Alcocer", "oneway": "yes", "postal_code": "28041"}}, {"type": "way", "id": 43263328, "nodes": [316438070, 3544594618, 3326943569, 3544594614, 248795319], "tags": {"highway": "secondary", "lanes": "4", "maxspeed": "50", "name": "Calle de Alcocer", "oneway": "yes", "postal_code": "28021", "surface": "asphalt"}}, {"type": "way", "id": 71599003, "nodes": [26282205, 1437771417, 248795163], "tags": {"highway": "secondary", "maxspeed": "50", "name": "Calle de Alcocer", "oneway": "yes", "postal_code": "28041"}}, {"type": "way", "id": 158851755, "nodes": [6179458828, 1709862099, 3634109183, 1709862040, 3634109182, 3634109181, 3634109179, 3634109178, 3634109177, 3890266110, 3890266109, 3890266100, 3890266066, 3890265754, 3890265749], "tags": {"highway": "cycleway"}}, {"type": "way", "id": 158851758, "nodes": [316438070, 1709862032, 1709862037, 3544594124, 306258360], "tags": {"highway": "tertiary", "name": "Calle de Santiago Am\u00f3n", "oneway": "yes", "postal_code": "28021"}}, {"type": "way", "id": 326918610, "nodes": [3336274715, 3336274707, 3336274708, 3336274709, 6179458826, 6179458825, 6179458824, 3336274710, 3336274711, 6179458823, 3336274712, 3336274713, 3336274714, 6179458822, 6179458820, 6179458821, 3336274715], "tags": {"area": "yes", "area:highway": "traffic_island", "highway": "pedestrian", "lit": "yes", "postal_code": "28021", "surface": "paved"}}, {"type": "way", "id": 342714793, "nodes": [3496820547, 3494953488, 3496820542, 248795318, 6652847265, 3496820532], "tags": {"footway": "crossing", "highway": "footway"}}, {"type": "way", "id": 344505772, "nodes": [3494953462, 6654945678, 1709862078, 3512394990, 3494953467, 3544594148, 3544594154, 3544594164, 1709862110, 3494953482, 3544594581, 6649990969, 3512395027], "tags": {"highway": "footway", "lit": "yes", "surface": "ground", "width": "5"}}, {"type": "way", "id": 345969029, "nodes": [11772637023, 3512395023, 3496820499, 6657552394, 3544594611, 3496820518, 3547342573, 3496820529], "tags": {"highway": "footway", "lit": "yes"}}, {"type": "way", "id": 348328511, "nodes": [3544594611, 3544594595], "tags": {"highway": "footway", "lit": "yes"}}, {"type": "way", "id": 348328514, "nodes": [3544594601, 3544594612], "tags": {"highway": "footway", "lit": "yes"}}, {"type": "way", "id": 348328515, "nodes": [3544594612, 6652847234, 3496820532], "tags": {"footway": "crossing", "highway": "footway"}}, {"type": "way", "id": 348328521, "nodes": [3496820529, 6652847248, 1709862053, 3496820541], "tags": {"footway": "crossing", "highway": "footway", "lit": "yes"}}, {"type": "way", "id": 348682095, "nodes": [6660573595, 6660573587, 6660573594, 6660553423, 6654975680, 3547342536, 6654975682, 3550750764, 3547342547, 3547342559, 3544594606, 3547342548, 3547342530, 6660573595], "tags": {"area": "yes", "highway": "pedestrian", "postal_code": "28021"}}, {"type": "way", "id": 358182730, "nodes": [3631478885, 3631478888], "tags": {"highway": "service", "service": "parking_aisle"}}, {"type": "way", "id": 358182732, "nodes": [3631478884, 3637129000, 3637129001, 3631478885], "tags": {"highway": "service", "service": "parking_aisle"}}, {"type": "way", "id": 358182734, "nodes": [3631474535, 3631474536, 3634110497, 3631474537], "tags": {"highway": "footway", "lit": "yes"}}, {"type": "way", "id": 358182736, "nodes": [3631478857, 3634110547, 3631478640, 3634110534, 3634110523], "tags": {"highway": "footway"}}, {"type": "way", "id": 358182737, "nodes": [3631478806, 3631478808, 3634110552, 3637128969, 3631478810], "tags": {"highway": "footway", "lit": "yes"}}, {"type": "way", "id": 358182740, "nodes": [3631474514, 3631474537, 3634110521], "tags": {"highway": "footway"}}, {"type": "way", "id": 358182742, "nodes": [3631478891, 3631479094, 3631479095, 3631479096], "tags": {"highway": "footway", "lit": "yes"}}, {"type": "way", "id": 358182743, "nodes": [3631478639, 3634110546, 3631478810, 3631478856], "tags": {"highway": "footway"}}, {"type": "way", "id": 358182747, "nodes": [3631474516, 3631474509, 3631474505, 3631474502, 3631474504, 3496820526], "tags": {"highway": "footway"}}, {"type": "way", "id": 358182748, "nodes": [3631478885, 3631479136, 3631479306, 3631479310, 3631479302, 3631479176, 3631479096, 3631478884], "tags": {"highway": "service", "service": "parking_aisle"}}, {"type": "way", "id": 358182750, "nodes": [3496820540, 3631474523, 3631474553, 3634110535, 3631478677, 3631478841, 3631478872], "tags": {"highway": "footway"}}, {"type": "way", "id": 358500388, "nodes": [3634110567, 3634110560, 3634110551, 3634110543, 3634110540, 12218920865, 3634110530, 3634110525, 3634110509, 3496820550, 3634110501, 6179458833], "tags": {"highway": "cycleway", "lit": "yes"}}, {"type": "way", "id": 358500390, "nodes": [3634110505, 3634110501], "tags": {"highway": "footway"}}, {"type": "way", "id": 358500392, "nodes": [3634110534, 3634110535], "tags": {"highway": "footway"}}, {"type": "way", "id": 358500393, "nodes": [3631478857, 3631478869], "tags": {"highway": "footway", "lit": "yes"}}, {"type": "way", "id": 358500395, "nodes": [3634110533, 3634110519], "tags": {"highway": "footway"}}, {"type": "way", "id": 358500396, "nodes": [3634110507, 3631474515], "tags": {"highway": "footway"}}, {"type": "way", "id": 358500400, "nodes": [3631478855, 3631478856, 3631478857], "tags": {"highway": "footway", "lit": "yes"}}, {"type": "way", "id": 358500401, "nodes": [3631478677, 3634110547, 3634110546], "tags": {"highway": "footway"}}, {"type": "way", "id": 358500403, "nodes": [3631479102, 3631479137, 3631479322], "tags": {"highway": "footway", "lit": "yes"}}, {"type": "way", "id": 358500404, "nodes": [3631478871, 3631479104, 3631479102], "tags": {"highway": "footway", "lit": "yes"}}, {"type": "way", "id": 358500405, "nodes": [3631478869, 3631478871, 3631478872], "tags": {"highway": "footway", "lit": "yes"}}, {"type": "way", "id": 358500406, "nodes": [3496820547, 3496820544, 3496820546, 3496820541, 3631474516, 3496820540, 3631474515, 3631474514, 3496820534, 3496820527, 3496820526, 3631474510], "tags": {"highway": "footway", "lit": "yes"}}, {"type": "way", "id": 358500407, "nodes": [3634110523, 3634110522, 3634110506, 3634110507], "tags": {"highway": "footway"}}, {"type": "way", "id": 358500408, "nodes": [3631478636, 3634110541, 3631478639, 3631478640], "tags": {"highway": "footway"}}, {"type": "way", "id": 358500409, "nodes": [3634110522, 3634110521, 3634110519, 3634110518], "tags": {"highway": "footway"}}, {"type": "way", "id": 358500411, "nodes": [3634110508, 3634110505, 3634110502, 3637128627, 3634110500, 3496820546], "tags": {"highway": "footway"}}, {"type": "way", "id": 358893182, "nodes": [3637129223, 3637129213, 3637129059, 3637129050, 11772637001, 3637129010, 3637128995, 3637128982, 3637128961, 3637128947, 3637128678, 3637128646], "tags": {"highway": "footway"}}, {"type": "way", "id": 358893183, "nodes": [3637129222, 3637129210, 3637129058, 3637129049, 3637129005, 3637128993, 3637128960, 3637128944, 3637128670, 3637128644, 3637128646], "tags": {"highway": "footway"}}, {"type": "way", "id": 358893185, "nodes": [3637128627, 3637128628, 3637128630, 3637128635, 3637128680, 3637128905, 3637128970, 3637129011, 3637129024, 11772636998, 3637129069, 3637129083, 3637129224], "tags": {"highway": "footway"}}, {"type": "way", "id": 358893189, "nodes": [3637128960, 3637128961], "tags": {"highway": "footway"}}, {"type": "way", "id": 358893198, "nodes": [3496820563, 3637128685], "tags": {"highway": "footway"}}, {"type": "way", "id": 358893199, "nodes": [3637129005, 3637129010], "tags": {"highway": "footway"}}, {"type": "way", "id": 358893200, "nodes": [3637129025, 3637129024], "tags": {"highway": "footway"}}, {"type": "way", "id": 358893208, "nodes": [3637128905, 3637128907], "tags": {"highway": "footway"}}, {"type": "way", "id": 358893209, "nodes": [10699707658, 3637128970, 3637128971], "tags": {"highway": "service"}}, {"type": "way", "id": 358893213, "nodes": [3637128947, 3637128944], "tags": {"highway": "footway"}}, {"type": "way", "id": 358893216, "nodes": [3637129011, 3637129013], "tags": {"highway": "footway"}}, {"type": "way", "id": 358893218, "nodes": [3637128993, 3637128995], "tags": {"highway": "footway"}}, {"type": "way", "id": 358893219, "nodes": [3637128670, 3637128678], "tags": {"highway": "footway"}}, {"type": "way", "id": 358893221, "nodes": [3637128680, 3637128683], "tags": {"highway": "footway"}}, {"type": "way", "id": 358893225, "nodes": [3637129056, 3637129073, 3637129070, 3637129014, 3637129002, 3637128948, 3637128928, 3637128913, 3637128902, 3637128900, 3637128904, 3637128914, 3637128924, 3637128958, 3637129026, 3637129027, 3637129074, 3637129072, 3637129086, 3637129225, 3496820831], "tags": {"highway": "footway"}}, {"type": "way", "id": 358893227, "nodes": [3637128914, 3637128685, 3637128636], "tags": {"highway": "footway"}}, {"type": "way", "id": 358893234, "nodes": [3637129071, 3637129072, 3637129026, 3637129025], "tags": {"highway": "footway", "lit": "yes"}}, {"type": "way", "id": 358893238, "nodes": [3637128913, 3637128894, 3637128664, 3637128658, 3637128643, 3637128636, 3634110501], "tags": {"footway": "sidewalk", "highway": "footway", "name": "Avenida de Andaluc\u00eda"}}, {"type": "way", "id": 358893240, "nodes": [3637129025, 3637129013, 3637128971, 3637128907, 3637128683, 3496820563, 3637128651, 3634110508], "tags": {"highway": "footway", "lit": "yes"}}, {"type": "way", "id": 422215392, "nodes": [248795319, 316438306], "tags": {"highway": "secondary", "lanes": "4", "maxspeed": "50", "name": "Calle de Alcocer", "oneway": "yes", "postal_code": "28021"}}, {"type": "way", "id": 660003675, "nodes": [6179458833, 6179458832, 6179458831, 6179458830, 6179458829, 6652847266, 6652847270, 6179458828], "tags": {"crossing": "marked", "crossing:markings": "yes", "cycleway": "crossing", "highway": "cycleway"}}, {"type": "way", "id": 707650441, "nodes": [3494953485, 6650007828, 3547342542, 6650007827, 6650007826, 6650007825, 6650007824, 6650007823, 3544594612], "tags": {"footway": "sidewalk", "highway": "footway"}}, {"type": "way", "id": 708011087, "nodes": [3496820529, 3512395027, 6652847237, 6652847236, 6652847235, 6652847234, 6652847233, 6652847232, 6652847231, 6654975663], "tags": {"highway": "footway", "surface": "paved"}}, {"type": "way", "id": 1267580574, "nodes": [11772637001, 11772637000, 11772636999, 11772636998], "tags": {"footway": "crossing", "highway": "footway"}}, {"type": "way", "id": 1270414937, "nodes": [3634110501, 3496820547], "tags": {"footway": "sidewalk", "highway": "footway", "name": "Avenida de Andaluc\u00eda"}}, {"type": "way", "id": 1270414938, "nodes": [11795819596, 11795819602, 11795819601, 11795819600, 11795819599, 11795819598, 11795819597, 3637128913], "tags": {"footway": "sidewalk", "highway": "footway", "name": "Avenida de Andaluc\u00eda"}}, {"type": "way", "id": 1270414939, "nodes": [3544594612, 6650007822, 6650007821, 6650007820, 6650007819, 6650007829, 6649990969], "tags": {"highway": "footway"}}]}