{"version": 0.6, "generator": "Overpass API 0.7.62.5 1bd436f1", "osm3s": {"timestamp_osm_base": "2025-03-23T10:23:16Z", "copyright": "The data included in this document is from www.openstreetmap.org. The data is made available under ODbL."}, "elements": [{"type": "node", "id": 21682622, "lat": 40.4804191, "lon": -3.7126429, "tags": {"crossing": "no", "highway": "traffic_signals"}}, {"type": "node", "id": 25587438, "lat": 40.4814931, "lon": -3.7054004}, {"type": "node", "id": 25687296, "lat": 40.4798941, "lon": -3.7124519}, {"type": "node", "id": 25687297, "lat": 40.4803222, "lon": -3.712592, "tags": {"crossing": "no", "highway": "traffic_signals"}}, {"type": "node", "id": 25920539, "lat": 40.4815792, "lon": -3.7084382}, {"type": "node", "id": 25920582, "lat": 40.4813417, "lon": -3.7095954}, {"type": "node", "id": 25920598, "lat": 40.4806739, "lon": -3.7093492, "tags": {"highway": "traffic_signals"}}, {"type": "node", "id": 25920600, "lat": 40.4807028, "lon": -3.7127893}, {"type": "node", "id": 26232930, "lat": 40.4805449, "lon": -3.7099432}, {"type": "node", "id": 26232951, "lat": 40.4805767, "lon": -3.7097959}, {"type": "node", "id": 26233247, "lat": 40.4811657, "lon": -3.7070387}, {"type": "node", "id": 41038654, "lat": 40.4800248, "lon": -3.7104792}, {"type": "node", "id": 41038862, "lat": 40.4798091, "lon": -3.7121791}, {"type": "node", "id": 41038866, "lat": 40.4799618, "lon": -3.7115577}, {"type": "node", "id": 41038867, "lat": 40.4800304, "lon": -3.7112594}, {"type": "node", "id": 41038868, "lat": 40.4800747, "lon": -3.7110603}, {"type": "node", "id": 41038869, "lat": 40.4801843, "lon": -3.7105399}, {"type": "node", "id": 41038870, "lat": 40.4802825, "lon": -3.7100246}, {"type": "node", "id": 161891034, "lat": 40.4802785, "lon": -3.7123887}, {"type": "node", "id": 161891036, "lat": 40.480467, "lon": -3.711414}, {"type": "node", "id": 161891037, "lat": 40.4808525, "lon": -3.709994}, {"type": "node", "id": 355161009, "lat": 40.4811997, "lon": -3.7100046}, {"type": "node", "id": 388039880, "lat": 40.4812106, "lon": -3.7132562}, {"type": "node", "id": 388039883, "lat": 40.4809832, "lon": -3.7099247, "tags": {"button_operated": "no", "crossing": "traffic_signals", "crossing:island": "yes", "crossing:markings": "dots", "highway": "crossing", "tactile_paving": "yes", "traffic_signals:sound": "no;yes", "traffic_signals:vibration": "no"}}, {"type": "node", "id": 388039885, "lat": 40.4806689, "lon": -3.7118427}, {"type": "node", "id": 388039886, "lat": 40.4806119, "lon": -3.7122485}, {"type": "node", "id": 388039887, "lat": 40.4806609, "lon": -3.7126721}, {"type": "node", "id": 388039888, "lat": 40.4808648, "lon": -3.7129821}, {"type": "node", "id": 992006655, "lat": 40.480558, "lon": -3.7119683, "tags": {"note": "SEM TYPH Madrid Av Ilustraci\u00f3n CRUCE Betanzos DIR A-6 CL"}}, {"type": "node", "id": 1115933678, "lat": 40.4809371, "lon": -3.7130772}, {"type": "node", "id": 1115933688, "lat": 40.478031, "lon": -3.7120786}, {"type": "node", "id": 1115933772, "lat": 40.4807466, "lon": -3.7095988}, {"type": "node", "id": 1115933801, "lat": 40.4807673, "lon": -3.7089331, "tags": {"button_operated": "no", "crossing": "traffic_signals", "highway": "crossing", "tactile_paving": "yes", "traffic_signals:sound": "yes", "traffic_signals:vibration": "no"}}, {"type": "node", "id": 1115933809, "lat": 40.4810031, "lon": -3.7100206}, {"type": "node", "id": 1115933937, "lat": 40.4797055, "lon": -3.7124844}, {"type": "node", "id": 1115934028, "lat": 40.4806273, "lon": -3.7095592, "tags": {"button_operated": "no", "crossing": "traffic_signals", "highway": "crossing", "tactile_paving": "yes", "traffic_signals:sound": "yes", "traffic_signals:vibration": "no"}}, {"type": "node", "id": 1115934029, "lat": 40.4810658, "lon": -3.7113754}, {"type": "node", "id": 1115934197, "lat": 40.480789, "lon": -3.7127568}, {"type": "node", "id": 1115934202, "lat": 40.480633, "lon": -3.7127607, "tags": {"button_operated": "no", "check_date:crossing": "2023-01-21", "crossing": "no", "highway": "traffic_signals", "tactile_paving": "yes", "traffic_signals:sound": "yes", "traffic_signals:vibration": "no"}}, {"type": "node", "id": 1115934211, "lat": 40.4812595, "lon": -3.710027, "tags": {"crossing": "traffic_signals", "highway": "crossing", "tactile_paving": "yes", "traffic_signals:sound": "no"}}, {"type": "node", "id": 1115934291, "lat": 40.4809496, "lon": -3.7129022, "tags": {"button_operated": "no", "crossing": "traffic_signals", "highway": "crossing", "tactile_paving": "yes", "traffic_signals:sound": "yes", "traffic_signals:vibration": "no"}}, {"type": "node", "id": 1115934331, "lat": 40.4803595, "lon": -3.7124617, "tags": {"crossing": "no", "highway": "traffic_signals"}}, {"type": "node", "id": 1115934387, "lat": 40.480458, "lon": -3.7124763, "tags": {"crossing": "no", "highway": "traffic_signals"}}, {"type": "node", "id": 1115934411, "lat": 40.4807851, "lon": -3.7126591}, {"type": "node", "id": 1115934421, "lat": 40.4802006, "lon": -3.7123683}, {"type": "node", "id": 1115934425, "lat": 40.4795571, "lon": -3.7126088}, {"type": "node", "id": 1115934453, "lat": 40.4813325, "lon": -3.710051}, {"type": "node", "id": 1115934468, "lat": 40.4809325, "lon": -3.7129727}, {"type": "node", "id": 1115934479, "lat": 40.4807332, "lon": -3.712628, "tags": {"button_operated": "no", "check_date:crossing": "2023-01-21", "crossing": "traffic_signals", "highway": "crossing", "tactile_paving": "yes", "traffic_signals:sound": "yes", "traffic_signals:vibration": "no"}}, {"type": "node", "id": 1115934523, "lat": 40.480659, "lon": -3.7125932}, {"type": "node", "id": 1115934565, "lat": 40.4807366, "lon": -3.7098457}, {"type": "node", "id": 1115934574, "lat": 40.4809584, "lon": -3.7104386}, {"type": "node", "id": 1115934579, "lat": 40.4802062, "lon": -3.7124255}, {"type": "node", "id": 1115934601, "lat": 40.4809723, "lon": -3.7128289}, {"type": "node", "id": 1115934620, "lat": 40.4815014, "lon": -3.7091908}, {"type": "node", "id": 1115934629, "lat": 40.4779613, "lon": -3.712054}, {"type": "node", "id": 1115934671, "lat": 40.4805996, "lon": -3.7108204}, {"type": "node", "id": 1125437823, "lat": 40.4814475, "lon": -3.7056514, "tags": {"button_operated": "no", "crossing": "traffic_signals", "crossing:signals": "yes", "highway": "crossing", "tactile_paving": "yes", "traffic_signals:sound": "yes", "traffic_signals:vibration": "no"}}, {"type": "node", "id": 1873271534, "lat": 40.4812777, "lon": -3.7132575}, {"type": "node", "id": 1873271536, "lat": 40.4814224, "lon": -3.7133257}, {"type": "node", "id": 1989017093, "lat": 40.481499, "lon": -3.7119624}, {"type": "node", "id": 1989017094, "lat": 40.4811627, "lon": -3.7116778}, {"type": "node", "id": 1989017095, "lat": 40.481471, "lon": -3.7120929}, {"type": "node", "id": 1989017096, "lat": 40.4811328, "lon": -3.7118214}, {"type": "node", "id": 1989017097, "lat": 40.4809377, "lon": -3.7115868}, {"type": "node", "id": 1989017098, "lat": 40.4811058, "lon": -3.7119507}, {"type": "node", "id": 1989017099, "lat": 40.4815281, "lon": -3.7118273}, {"type": "node", "id": 2267506971, "lat": 40.481009, "lon": -3.7116173}, {"type": "node", "id": 2590729422, "lat": 40.4800592, "lon": -3.7123625}, {"type": "node", "id": 2594918866, "lat": 40.4809311, "lon": -3.7101294}, {"type": "node", "id": 2918457229, "lat": 40.4808255, "lon": -3.7121728}, {"type": "node", "id": 2918457234, "lat": 40.4815477, "lon": -3.7119911}, {"type": "node", "id": 3138342830, "lat": 40.4807935, "lon": -3.712897}, {"type": "node", "id": 3138343129, "lat": 40.480612, "lon": -3.7125251}, {"type": "node", "id": 3461979410, "lat": 40.4804102, "lon": -3.7124658}, {"type": "node", "id": 3463210726, "lat": 40.4813207, "lon": -3.706267}, {"type": "node", "id": 3476657593, "lat": 40.4808882, "lon": -3.7121962}, {"type": "node", "id": 3563628424, "lat": 40.4804491, "lon": -3.7111314}, {"type": "node", "id": 3563628433, "lat": 40.4800375, "lon": -3.7122126}, {"type": "node", "id": 3563628434, "lat": 40.480171, "lon": -3.7115011}, {"type": "node", "id": 3563628435, "lat": 40.4802308, "lon": -3.7112029}, {"type": "node", "id": 3563628436, "lat": 40.480284, "lon": -3.7109536}, {"type": "node", "id": 3563628437, "lat": 40.4803307, "lon": -3.7107292}, {"type": "node", "id": 3563628438, "lat": 40.4804015, "lon": -3.7103859}, {"type": "node", "id": 3563628439, "lat": 40.4804255, "lon": -3.7102411}, {"type": "node", "id": 3563628440, "lat": 40.480446, "lon": -3.710127}, {"type": "node", "id": 3563628441, "lat": 40.4804547, "lon": -3.7100513}, {"type": "node", "id": 3563628442, "lat": 40.4804584, "lon": -3.709941}, {"type": "node", "id": 3563628443, "lat": 40.4804589, "lon": -3.7099013}, {"type": "node", "id": 3564247602, "lat": 40.4816652, "lon": -3.708561}, {"type": "node", "id": 3564519697, "lat": 40.4817721, "lon": -3.713412}, {"type": "node", "id": 3564528208, "lat": 40.4809898, "lon": -3.7101636}, {"type": "node", "id": 3571561309, "lat": 40.4813459, "lon": -3.7132911}, {"type": "node", "id": 3571561357, "lat": 40.4816985, "lon": -3.7134572}, {"type": "node", "id": 3571561365, "lat": 40.4809339, "lon": -3.7130054}, {"type": "node", "id": 3622172126, "lat": 40.4805118, "lon": -3.7124913, "tags": {"button_operated": "no", "crossing": "traffic_signals", "crossing:island": "yes", "highway": "crossing", "tactile_paving": "yes", "traffic_signals:sound": "yes", "traffic_signals:vibration": "no"}}, {"type": "node", "id": 3622172127, "lat": 40.4805817, "lon": -3.7113513}, {"type": "node", "id": 3622172128, "lat": 40.4804706, "lon": -3.7119078}, {"type": "node", "id": 3622172129, "lat": 40.4806949, "lon": -3.7107982}, {"type": "node", "id": 3622172130, "lat": 40.4807504, "lon": -3.7105259}, {"type": "node", "id": 3622172131, "lat": 40.4806775, "lon": -3.7105714, "tags": {"highway": "give_way"}}, {"type": "node", "id": 3622172132, "lat": 40.4807278, "lon": -3.7103714}, {"type": "node", "id": 3622172133, "lat": 40.4808042, "lon": -3.7100877}, {"type": "node", "id": 3622172134, "lat": 40.4807685, "lon": -3.7101965}, {"type": "node", "id": 3622172135, "lat": 40.4808272, "lon": -3.7111203}, {"type": "node", "id": 3622172136, "lat": 40.4808982, "lon": -3.7107535}, {"type": "node", "id": 3622172137, "lat": 40.4809334, "lon": -3.7105755}, {"type": "node", "id": 3622172139, "lat": 40.4809788, "lon": -3.7102767}, {"type": "node", "id": 3629913846, "lat": 40.4803076, "lon": -3.7124626, "tags": {"button_operated": "no", "crossing": "traffic_signals", "crossing:island": "yes", "highway": "crossing", "tactile_paving": "yes", "traffic_signals:sound": "yes", "traffic_signals:vibration": "no"}}, {"type": "node", "id": 3635949234, "lat": 40.4806193, "lon": -3.7128302}, {"type": "node", "id": 4302045422, "lat": 40.4814404, "lon": -3.7056837, "tags": {"highway": "traffic_signals", "traffic_signals": "traffic_lights", "traffic_signals:direction": "forward"}}, {"type": "node", "id": 4784710153, "lat": 40.4800231, "lon": -3.7122842}, {"type": "node", "id": 4831157767, "lat": 40.481554, "lon": -3.7111509}, {"type": "node", "id": 4831157768, "lat": 40.4812302, "lon": -3.7110447}, {"type": "node", "id": 4831157769, "lat": 40.4810579, "lon": -3.711004}, {"type": "node", "id": 4831161072, "lat": 40.4814175, "lon": -3.712562}, {"type": "node", "id": 4831161073, "lat": 40.4808105, "lon": -3.7122468}, {"type": "node", "id": 4831161074, "lat": 40.4808669, "lon": -3.7122754}, {"type": "node", "id": 4831161075, "lat": 40.4809494, "lon": -3.71153}, {"type": "node", "id": 4831161076, "lat": 40.4810193, "lon": -3.711566}, {"type": "node", "id": 4831161077, "lat": 40.4815871, "lon": -3.7117886}, {"type": "node", "id": 4831161078, "lat": 40.4814361, "lon": -3.7124889}, {"type": "node", "id": 4831161079, "lat": 40.4811368, "lon": -3.7110226}, {"type": "node", "id": 5825114003, "lat": 40.4816494, "lon": -3.7089388}, {"type": "node", "id": 5825114005, "lat": 40.4815637, "lon": -3.7089123}, {"type": "node", "id": 5825114007, "lat": 40.4812187, "lon": -3.711042}, {"type": "node", "id": 5825114008, "lat": 40.4810794, "lon": -3.7115896}, {"type": "node", "id": 6176967002, "lat": 40.4817214, "lon": -3.7085873}, {"type": "node", "id": 6176989755, "lat": 40.4800283, "lon": -3.7122611}, {"type": "node", "id": 6176989764, "lat": 40.4785694, "lon": -3.7122764}, {"type": "node", "id": 8701490673, "lat": 40.481587, "lon": -3.7092436}, {"type": "node", "id": 8739955102, "lat": 40.4806072, "lon": -3.7123888}, {"type": "node", "id": 8739955103, "lat": 40.4806301, "lon": -3.7120934}, {"type": "node", "id": 8739955108, "lat": 40.4806183, "lon": -3.7107596}, {"type": "node", "id": 8739961517, "lat": 40.480757, "lon": -3.7094455}, {"type": "node", "id": 11458394564, "lat": 40.477982, "lon": -3.7119393}, {"type": "node", "id": 11458394565, "lat": 40.4780349, "lon": -3.7116679}, {"type": "node", "id": 11458394567, "lat": 40.4782714, "lon": -3.7104674}, {"type": "node", "id": 11458504977, "lat": 40.4790987, "lon": -3.7124652}, {"type": "node", "id": 11458504978, "lat": 40.4795239, "lon": -3.712607}, {"type": "node", "id": 11458504982, "lat": 40.4798208, "lon": -3.7123641}, {"type": "node", "id": 11458504983, "lat": 40.4797708, "lon": -3.7124014}, {"type": "node", "id": 11458504986, "lat": 40.4799052, "lon": -3.7123338}, {"type": "node", "id": 11458504990, "lat": 40.4799959, "lon": -3.7123153}, {"type": "node", "id": 11458504991, "lat": 40.4800121, "lon": -3.7123024}, {"type": "node", "id": 11458505075, "lat": 40.4799709, "lon": -3.7124016}, {"type": "node", "id": 11458505076, "lat": 40.4800377, "lon": -3.7123789}, {"type": "node", "id": 11458505079, "lat": 40.4800692, "lon": -3.7123413, "tags": {"crossing": "traffic_signals", "highway": "crossing", "traffic_signals": "traffic_lights", "traffic_signals:direction": "forward"}}, {"type": "node", "id": 11458505081, "lat": 40.4804645, "lon": -3.7124449, "tags": {"crossing": "traffic_signals", "highway": "crossing", "traffic_signals": "traffic_lights", "traffic_signals:direction": "forward"}}, {"type": "node", "id": 11458505082, "lat": 40.4803507, "lon": -3.7124925, "tags": {"crossing": "traffic_signals", "highway": "crossing", "traffic_signals": "traffic_lights", "traffic_signals:direction": "forward"}}, {"type": "node", "id": 11458505084, "lat": 40.4807408, "lon": -3.7125903, "tags": {"highway": "traffic_signals", "traffic_signals": "traffic_lights", "traffic_signals:direction": "forward"}}, {"type": "node", "id": 11676021656, "lat": 40.479652, "lon": -3.7125471}, {"type": "node", "id": 11676021668, "lat": 40.4800844, "lon": -3.7123073, "tags": {"button_operated": "no", "check_date:crossing": "2023-01-21", "crossing": "no", "highway": "traffic_signals", "tactile_paving": "yes", "traffic_signals:sound": "yes", "traffic_signals:vibration": "no"}}, {"type": "node", "id": 11676068171, "lat": 40.4801988, "lon": -3.7123996}, {"type": "node", "id": 11748641741, "lat": 40.4812794, "lon": -3.7096297, "tags": {"barrier": "kerb", "kerb": "lowered", "tactile_paving": "yes", "wheelchair": "yes"}}, {"type": "node", "id": 11748641747, "lat": 40.4814341, "lon": -3.7091686, "tags": {"button_operated": "no", "crossing": "traffic_signals", "crossing:markings": "dots", "highway": "crossing", "tactile_paving": "yes", "traffic_signals:sound": "yes", "traffic_signals:vibration": "no"}}, {"type": "node", "id": 11748641748, "lat": 40.4814427, "lon": -3.7091282, "tags": {"highway": "traffic_signals", "traffic_signals": "traffic_lights", "traffic_signals:direction": "forward"}}, {"type": "node", "id": 11748681751, "lat": 40.4816316, "lon": -3.7085659}, {"type": "node", "id": 11748681752, "lat": 40.4816481, "lon": -3.7085557}, {"type": "node", "id": 12550889721, "lat": 40.4821557, "lon": -3.7058872}, {"type": "node", "id": 12550889722, "lat": 40.4821314, "lon": -3.7058758}, {"type": "node", "id": 12550889723, "lat": 40.4820777, "lon": -3.7058539}, {"type": "node", "id": 12550889724, "lat": 40.4818519, "lon": -3.7057713}, {"type": "node", "id": 12550889725, "lat": 40.4817493, "lon": -3.7057369}, {"type": "node", "id": 12550889726, "lat": 40.4815632, "lon": -3.7056726}, {"type": "node", "id": 12550889727, "lat": 40.4814499, "lon": -3.7059974}, {"type": "node", "id": 12550889728, "lat": 40.4812567, "lon": -3.7069303}, {"type": "node", "id": 12550889729, "lat": 40.4810815, "lon": -3.7077772}, {"type": "node", "id": 12550889730, "lat": 40.4809323, "lon": -3.7084789}, {"type": "node", "id": 12550889731, "lat": 40.4808328, "lon": -3.7089512}, {"type": "node", "id": 12550889732, "lat": 40.4807461, "lon": -3.7093766}, {"type": "node", "id": 12550889734, "lat": 40.4815076, "lon": -3.7057198}, {"type": "node", "id": 12550889735, "lat": 40.4815297, "lon": -3.7056641}, {"type": "node", "id": 12550889736, "lat": 40.4807051, "lon": -3.7095846}, {"type": "node", "id": 12550889737, "lat": 40.4806921, "lon": -3.7096369}, {"type": "node", "id": 12550889738, "lat": 40.4805364, "lon": -3.7104258}, {"type": "node", "id": 12550889739, "lat": 40.4803744, "lon": -3.711236}, {"type": "node", "id": 12550889740, "lat": 40.4802397, "lon": -3.7119063}, {"type": "node", "id": 12550889741, "lat": 40.4801512, "lon": -3.7123364}, {"type": "node", "id": 12550889742, "lat": 40.4801473, "lon": -3.7123631}, {"type": "node", "id": 12550889743, "lat": 40.4801621, "lon": -3.7124015}, {"type": "node", "id": 12550889744, "lat": 40.480176, "lon": -3.712416}, {"type": "node", "id": 12550889745, "lat": 40.4801803, "lon": -3.7124399}, {"type": "node", "id": 12550889746, "lat": 40.4801813, "lon": -3.7124903}, {"type": "node", "id": 12550889747, "lat": 40.4801746, "lon": -3.7125278}, {"type": "node", "id": 12550889748, "lat": 40.4801613, "lon": -3.7125886}, {"type": "node", "id": 12550889749, "lat": 40.4815232, "lon": -3.7056792}, {"type": "node", "id": 12550889750, "lat": 40.481544, "lon": -3.7056676}, {"type": "way", "id": 4292688, "nodes": [25687296, 11458505075, 11458505076, 2590729422, 11458505079, 11676021668, 26232930, 26232951, 1115934028, 25920598, 1115933801, 26233247, 3463210726, 4302045422, 1125437823, 25587438], "tags": {"highway": "residential", "lanes": "2", "maxspeed": "50", "name": "Paseo de la Vaguada", "oneway": "yes", "postal_code": "28029", "source": "PNOA", "source:date": "2009", "surface": "asphalt"}}, {"type": "way", "id": 5555173, "nodes": [41038862, 41038866, 41038867, 41038868, 41038869, 41038870], "tags": {"highway": "footway"}}, {"type": "way", "id": 5555178, "nodes": [41038869, 41038654], "tags": {"highway": "footway"}}, {"type": "way", "id": 16089279, "nodes": [161891034, 161891036, 1115934671, 8739955108, 3622172131, 3622172132, 3622172134, 3622172133, 161891037], "tags": {"highway": "trunk_link", "lanes": "1", "oneway": "yes", "surface": "asphalt"}}, {"type": "way", "id": 33870751, "nodes": [388039883, 1115933809, 3564528208, 3622172139, 1115934574, 3622172137, 3622172136, 3622172135, 388039885], "tags": {"destination:ref": "M-40", "destination:street": "Avenida Ventisquero de la Condesa", "highway": "trunk_link", "lanes": "1", "maxspeed": "40", "oneway": "yes", "surface": "asphalt"}}, {"type": "way", "id": 33870752, "nodes": [388039885, 8739955103, 388039886, 8739955102, 3138343129, 388039887, 3138342830, 388039888, 388039880], "tags": {"highway": "trunk_link", "lanes": "1", "layer": "-2", "maxspeed": "50", "name": "T\u00fanel de Ventisquero de la Condesa", "oneway": "yes", "surface": "asphalt", "tunnel": "yes"}}, {"type": "way", "id": 42636672, "nodes": [25687297, 11458505082, 1115934331, 3622172128, 3622172127, 3622172129, 3622172130, 161891037], "tags": {"highway": "trunk", "lanes": "3", "maxspeed": "50", "name": "Avenida de la Ilustraci\u00f3n", "oneway": "yes", "ref": "M-30", "source": "PNOA", "source:date": "2009", "surface": "asphalt"}}, {"type": "way", "id": 96268446, "nodes": [11458394567, 11458394565, 11458394564, 1115934629, 1115933688, 6176989764, 11458504977, 11458504978, 1115934425, 11676021656, 1115933937, 11458504983, 11458504982, 11458504986, 11458504990, 11458504991, 4784710153, 6176989755, 3563628433, 3563628434, 3563628435, 3563628436, 3563628437, 3563628438, 3563628439, 3563628440, 3563628441, 3563628442, 3563628443], "tags": {"footway": "sidewalk", "highway": "footway", "lit": "yes", "source": "PNOA", "source:date": "2009", "surface": "paving_stones"}}, {"type": "way", "id": 119023654, "nodes": [25920539, 11748641748, 11748641747, 25920582, 1115934211, 4831157769, 4831161075, 1989017097, 2918457229, 4831161073, 11458505084, 1115934479, 25920600], "tags": {"highway": "residential", "lanes": "1", "lit": "yes", "maxspeed": "50", "name": "Calle de Santiago de Compostela", "oneway": "yes", "postal_code": "28029", "sidewalk": "both", "source": "PNOA", "source:date": "2009", "surface": "asphalt"}}, {"type": "way", "id": 188282029, "nodes": [1989017093, 1989017096], "tags": {"highway": "service", "lanes": "1", "oneway": "no", "service": "parking_aisle", "surface": "concrete"}}, {"type": "way", "id": 188282030, "nodes": [1989017094, 1989017096, 1989017098, 1989017095, 1989017093, 1989017099, 1989017094, 2267506971, 1989017097], "tags": {"highway": "service", "lanes": "1", "name": "Plaza de Villafranca de los Barros", "oneway": "no", "service": "parking_aisle", "surface": "concrete"}}, {"type": "way", "id": 350662798, "nodes": [3564247602, 11748681752, 11748681751, 5825114005, 1115934620, 1115934453, 4831161079, 1115934029, 4831161076, 2267506971, 3476657593, 4831161074, 1115934411, 1115934197, 1115934601, 1115934291, 1115934468, 3571561365, 1115933678, 1873271534, 3571561309, 1873271536, 3571561357, 3564519697], "tags": {"footway": "sidewalk", "highway": "footway"}}, {"type": "way", "id": 490950604, "nodes": [4831157769, 4831161079, 5825114007, 4831157768, 4831157767], "tags": {"highway": "footway", "surface": "paving_stones"}}, {"type": "way", "id": 490950955, "nodes": [4831161073, 4831161074, 4831161072, 4831161078, 2918457234, 4831161077, 5825114008, 4831161076, 4831161075], "tags": {"highway": "footway", "surface": "paving_stones"}}, {"type": "way", "id": 616088810, "nodes": [6176967002, 5825114003, 8701490673, 5825114007, 5825114008], "tags": {"highway": "footway", "surface": "paving_stones"}}, {"type": "way", "id": 943963203, "nodes": [1115934411, 1115934479, 1115934523, 3622172126, 1115934387, 3461979410, 1115934331, 3629913846, 1115934579, 11676068171, 1115934421, 3563628424, 1115934565, 1115933772, 8739961517], "tags": {"footway": "sidewalk", "highway": "footway", "lit": "yes", "source": "PNOA", "source:date": "2009", "surface": "paving_stones"}}, {"type": "way", "id": 1264591392, "nodes": [3635949234, 1115934202, 1115934523, 355161009, 11748641741], "tags": {"highway": "footway", "source": "PNOA", "source:date": "2009", "surface": "sand"}}, {"type": "way", "id": 1349204065, "nodes": [388039883, 2594918866, 992006655, 11458505081, 1115934387, 21682622], "tags": {"foot": "no", "highway": "trunk", "lanes": "3", "maxspeed": "50", "name": "Avenida de la Ilustraci\u00f3n", "oneway": "yes", "ref": "M-30", "source": "PNOA", "source:date": "2009", "surface": "asphalt"}}, {"type": "way", "id": 1356118811, "nodes": [12550889721, 12550889722, 12550889723, 12550889724, 12550889725, 12550889726, 12550889750, 12550889735, 12550889749, 12550889734, 12550889727, 12550889728, 12550889729, 12550889730, 12550889731, 12550889732, 12550889736, 12550889737, 12550889738, 12550889739, 12550889740, 12550889741, 12550889742, 12550889743, 12550889744, 12550889745, 12550889746, 12550889747, 12550889748], "tags": {"highway": "cycleway"}}]}